Workbook

Sheet Quarterly Financials
A1: Quarterly Financial Statements, Last 12 Quarters
B2: $ in thousands except per share.
A4: INCOME STATEMENT
C5: Q3 2023 | D5: Q4 2023 | E5: Q1 2024 | F5: Q2 2024 | G5: Q3 2024 | H5: Q4 2024 | I5: Q1 2025 | J5: Q2 2025 | K5: Q3 2025 | L5: Q4 2025 | M5: Q1 2026 | N5: Q2 2026 | O5: LTM
B6: Net revenues | C6: ='Qtr Source Data'!C6 -> 157854 | D6: ='Qtr Source Data'!E6-'Qtr Source Data'!D6 -> 187987 | E6: ='Qtr Source Data'!F6 -> 174350 | F6: ='Qtr Source Data'!G6 -> 163147 | G6: ='Qtr Source Data'!H6 -> 136593 | H6: ='Qtr Source Data'!J6-'Qtr Source Data'!I6 -> 143484 | I6: ='Qtr Source Data'!K6 -> 121387 | J6: ='Qtr Source Data'!L6 -> 105120 | K6: ='Qtr Source Data'!M6 -> 77742 | L6: ='Qtr Source Data'!O6-'Qtr Source Data'!N6 -> 72659 | M6: ='Qtr Source Data'!P6 -> 63262 | N6: ='Qtr Source Data'!Q6 -> 51849 | O6: =SUM(K6:N6) -> 265512
B7: YoY growth | C7: n/a | D7: n/a | E7: n/a | F7: n/a | G7: =IFERROR(G6/C6-1,"") -> -0.13468775 | H7: =IFERROR(H6/D6-1,"") -> -0.23673446 | I7: =IFERROR(I6/E6-1,"") -> -0.30377402 | J7: =IFERROR(J6/F6-1,"") -> -0.3556731 | K7: =IFERROR(K6/G6-1,"") -> -0.43084931 | L7: =IFERROR(L6/H6-1,"") -> -0.49360904 | M7: =IFERROR(M6/I6-1,"") -> -0.4788404 | N7: =IFERROR(N6/J6-1,"") -> -0.5067637
B8: Cost of revenues | C8: ='Qtr Source Data'!C7 -> 83575 | D8: ='Qtr Source Data'!E7-'Qtr Source Data'!D7 -> 45804 | E8: ='Qtr Source Data'!F7 -> 46497 | F8: ='Qtr Source Data'!G7 -> 45411 | G8: ='Qtr Source Data'!H7 -> 43420 | H8: ='Qtr Source Data'!J7-'Qtr Source Data'!I7 -> 45599 | I8: ='Qtr Source Data'!K7 -> 53973 | J8: ='Qtr Source Data'!L7 -> 35478 | K8: ='Qtr Source Data'!M7 -> 31701 | L8: ='Qtr Source Data'!O7-'Qtr Source Data'!N7 -> 30999 | M8: ='Qtr Source Data'!P7 -> 25374 | N8: ='Qtr Source Data'!Q7 -> 23567 | O8: =SUM(K8:N8) -> 111641
B9: Gross profit | C9: =C6-C8 -> 74279 | D9: =D6-D8 -> 142183 | E9: =E6-E8 -> 127853 | F9: =F6-F8 -> 117736 | G9: =G6-G8 -> 93173 | H9: =H6-H8 -> 97885 | I9: =I6-I8 -> 67414 | J9: =J6-J8 -> 69642 | ... O9: =O6-O8 -> 153871
B10: Gross margin | C10: =IFERROR(C9/C6,"") -> 0.47055507 | D10: =IFERROR(D9/D6,"") -> 0.75634485 | E10: =IFERROR(E9/E6,"") -> 0.7333123 | F10: =IFERROR(F9/F6,"") -> 0.72165593 | G10: =IFERROR(G9/G6,"") -> 0.68212134 | H10: =IFERROR(H9/H6,"") -> 0.6822015 | I10: =IFERROR(I9/I6,"") -> 0.55536425 | J10: =IFERROR(J9/J6,"") -> 0.6625 | ... O10: =IFERROR(O9/O6,"") -> 0.5795256
B11: Research and development | C11: ='Qtr Source Data'!C8 -> 46202 | D11: ='Qtr Source Data'!E8-'Qtr Source Data'!D8 -> 45724 | E11: ='Qtr Source Data'!F8 -> 44435 | F11: ='Qtr Source Data'!G8 -> 43651 | G11: ='Qtr Source Data'!H8 -> 41337 | H11: ='Qtr Source Data'!J8-'Qtr Source Data'!I8 -> 41008 | I11: ='Qtr Source Data'!K8 -> 29428 | J11: ='Qtr Source Data'!L8 -> 28717 | K11: ='Qtr Source Data'!M8 -> 18350 | L11: ='Qtr Source Data'!O8-'Qtr Source Data'!N8 -> 16958 | M11: ='Qtr Source Data'!P8 -> 9139 | N11: ='Qtr Source Data'!Q8 -> 7398 | O11: =SUM(K11:N11) -> 51845
B12: Sales and marketing | C12: ='Qtr Source Data'!C9 -> 28872 | D12: ='Qtr Source Data'!E9-'Qtr Source Data'!D9 -> 29746 | E12: ='Qtr Source Data'!F9 -> 30375 | F12: ='Qtr Source Data'!G9 -> 23545 | G12: ='Qtr Source Data'!H9 -> 26508 | H12: ='Qtr Source Data'!J9-'Qtr Source Data'!I9 -> 27901 | I12: ='Qtr Source Data'!K9 -> 25614 | J12: ='Qtr Source Data'!L9 -> 17417 | K12: ='Qtr Source Data'!M9 -> 11583 | L12: ='Qtr Source Data'!O9-'Qtr Source Data'!N9 -> 14140 | M12: ='Qtr Source Data'!P9 -> 10606 | N12: ='Qtr Source Data'!Q9 -> 9468 | O12: =SUM(K12:N12) -> 45797
B13: General and administrative | C13: ='Qtr Source Data'!C10 -> 53475 | D13: ='Qtr Source Data'!E10-'Qtr Source Data'!D10 -> 53426 | E13: ='Qtr Source Data'!F10 -> 55534 | F13: ='Qtr Source Data'!G10 -> 54016 | G13: ='Qtr Source Data'!H10 -> 51910 | H13: ='Qtr Source Data'!J10-'Qtr Source Data'!I10 -> 56296 | I13: ='Qtr Source Data'!K10 -> 39374 | J13: ='Qtr Source Data'!L10 -> 59966 | K13: ='Qtr Source Data'!M10 -> 33232 | L13: ='Qtr Source Data'!O10-'Qtr Source Data'!N10 -> 44834 | M13: ='Qtr Source Data'!P10 -> 19180 | N13: ='Qtr Source Data'!Q10 -> 14591 | O13: =SUM(K13:N13) -> 111837
B14: Impairment expense | C14: ='Qtr Source Data'!C11 -> 3600 | D14: ='Qtr Source Data'!E11-'Qtr Source Data'!D11 -> 0 | E14: ='Qtr Source Data'!F11 -> 0 | F14: ='Qtr Source Data'!G11 -> 481531 | G14: ='Qtr Source Data'!H11 -> 195708 | H14: ='Qtr Source Data'!J11-'Qtr Source Data'!I11 -> 0 | I14: ='Qtr Source Data'!K11 -> 2000 | J14: ='Qtr Source Data'!L11 -> 0 | K14: ='Qtr Source Data'!M11 -> 0 | L14: ='Qtr Source Data'!O11-'Qtr Source Data'!N11 -> 0 | M14: ='Qtr Source Data'!P11 -> 0 | N14: ='Qtr Source Data'!Q11 -> 0 | O14: =SUM(K14:N14) -> 0
B15: Total operating expenses | C15: =SUM(C11:C14) -> 132149 | D15: =SUM(D11:D14) -> 128896 | E15: =SUM(E11:E14) -> 130344 | F15: =SUM(F11:F14) -> 602743 | G15: =SUM(G11:G14) -> 315463 | H15: =SUM(H11:H14) -> 125205 | I15: =SUM(I11:I14) -> 96416 | J15: =SUM(J11:J14) -> 106100 | ... O15: =SUM(O11:O14) -> 209479
B16: Operating income (loss) | C16: =C9-C15 -> -57870 | D16: =D9-D15 -> 13287 | E16: =E9-E15 -> -2491 | F16: =F9-F15 -> -485007 | G16: =G9-G15 -> -222290 | H16: =H9-H15 -> -27320 | I16: =I9-I15 -> -29002 | J16: =J9-J15 -> -36458 | ... O16: =O9-O15 -> -55608
B17: Operating margin | C17: =IFERROR(C16/C6,"") -> -0.36660458 | D17: =IFERROR(D16/D6,"") -> 0.070680419 | E17: =IFERROR(E16/E6,"") -> -0.014287353 | F17: =IFERROR(F16/F6,"") -> -2.9728221 | G17: =IFERROR(G16/G6,"") -> -1.6273894 | H17: =IFERROR(H16/H6,"") -> -0.19040451 | I17: =IFERROR(I16/I6,"") -> -0.2389218 | J17: =IFERROR(J16/J6,"") -> -0.34682268 | ... O17: =IFERROR(O16/O6,"") -> -0.20943686
B18: Interest expense, net | C18: ='Qtr Source Data'!C12 -> -733 | D18: ='Qtr Source Data'!E12-'Qtr Source Data'!D12 -> -658 | E18: ='Qtr Source Data'!F12 -> -650 | F18: ='Qtr Source Data'!G12 -> -651 | G18: ='Qtr Source Data'!H12 -> -658 | H18: ='Qtr Source Data'!J12-'Qtr Source Data'!I12 -> -631 | I18: ='Qtr Source Data'!K12 -> -467 | J18: ='Qtr Source Data'!L12 -> -41 | K18: ='Qtr Source Data'!M12 -> -41 | L18: ='Qtr Source Data'!O12-'Qtr Source Data'!N12 -> -41 | M18: ='Qtr Source Data'!P12 -> -31 | N18: ='Qtr Source Data'!Q12 -> -22 | O18: =SUM(K18:N18) -> -135
B19: Other income, net | C19: ='Qtr Source Data'!C13 -> 40492 | D19: ='Qtr Source Data'!E13-'Qtr Source Data'!D13 -> 5139 | E19: ='Qtr Source Data'!F13 -> 10780 | F19: ='Qtr Source Data'!G13 -> 7119 | G19: ='Qtr Source Data'!H13 -> 7586 | H19: ='Qtr Source Data'!J13-'Qtr Source Data'!I13 -> 25847 | I19: ='Qtr Source Data'!K13 -> 12997 | J19: ='Qtr Source Data'!L13 -> 2059 | K19: ='Qtr Source Data'!M13 -> 1377 | L19: ='Qtr Source Data'!O13-'Qtr Source Data'!N13 -> 871 | M19: ='Qtr Source Data'!P13 -> 1156 | N19: ='Qtr Source Data'!Q13 -> 638 | O19: =SUM(K19:N19) -> 4042
B20: Income (loss) before income taxes | C20: =C16+C18+C19 -> -18111 | D20: =D16+D18+D19 -> 17768 | E20: =E16+E18+E19 -> 7639 | F20: =F16+F18+F19 -> -478539 | G20: =G16+G18+G19 -> -215362 | H20: =H16+H18+H19 -> -2104 | I20: =I16+I18+I19 -> -16472 | J20: =J16+J18+J19 -> -34440 | ... O20: =O16+O18+O19 -> -51701
B21: (Provision for) benefit from income taxes | C21: ='Qtr Source Data'!C14 -> -172 | D21: ='Qtr Source Data'!E14-'Qtr Source Data'!D14 -> -8103 | E21: ='Qtr Source Data'!F14 -> -9059 | F21: ='Qtr Source Data'!G14 -> -138345 | G21: ='Qtr Source Data'!H14 -> 2723 | H21: ='Qtr Source Data'!J14-'Qtr Source Data'!I14 -> -4021 | I21: ='Qtr Source Data'!K14 -> -1012 | J21: ='Qtr Source Data'!L14 -> -1223 | K21: ='Qtr Source Data'!M14 -> -1683 | L21: ='Qtr Source Data'!O14-'Qtr Source Data'!N14 -> 639 | M21: ='Qtr Source Data'!P14 -> 140 | N21: ='Qtr Source Data'!Q14 -> -392 | O21: =SUM(K21:N21) -> -1296
B22: Net income (loss) | C22: =C20+C21 -> -18283 | D22: =D20+D21 -> 9665 | E22: =E20+E21 -> -1420 | F22: =F20+F21 -> -616884 | G22: =G20+G21 -> -212639 | H22: =H20+H21 -> -6125 | I22: =I20+I21 -> -17484 | J22: =J20+J21 -> -35663 | ... O22: =O20+O21 -> -52997
B23: Net margin | C23: =IFERROR(C22/C6,"") -> -0.11582222 | D23: =IFERROR(D22/D6,"") -> 0.05141313 | E23: =IFERROR(E22/E6,"") -> -0.0081445369 | F23: =IFERROR(F22/F6,"") -> -3.7811544 | G23: =IFERROR(G22/G6,"") -> -1.5567342 | H23: =IFERROR(H22/H6,"") -> -0.042687686 | I23: =IFERROR(I22/I6,"") -> -0.14403519 | J23: =IFERROR(J22/J6,"") -> -0.33925989 | ... O23: =IFERROR(O22/O6,"") -> -0.19960303
B24: EPS, basic | C24: ='Qtr Source Data'!C16 -> -0.16 | D24: n/a | E24: ='Qtr Source Data'!F16 -> -0.01 | F24: ='Qtr Source Data'!G16 -> -6.01 | G24: ='Qtr Source Data'!H16 -> -2.05 | H24: n/a | I24: ='Qtr Source Data'!K16 -> -0.17 | J24: ='Qtr Source Data'!L16 -> -0.33 | K24: ='Qtr Source Data'!M16 -> -0.16 | L24: n/a | M24: ='Qtr Source Data'!P16 -> 0 | N24: ='Qtr Source Data'!Q16 -> -0.03
B25: EPS, diluted | C25: ='Qtr Source Data'!C17 -> -0.16 | D25: n/a | E25: ='Qtr Source Data'!F17 -> -0.01 | F25: ='Qtr Source Data'!G17 -> -6.01 | G25: ='Qtr Source Data'!H17 -> -2.05 | H25: n/a | I25: ='Qtr Source Data'!K17 -> -0.17 | J25: ='Qtr Source Data'!L17 -> -0.33 | K25: ='Qtr Source Data'!M17 -> -0.16 | L25: n/a | M25: ='Qtr Source Data'!P17 -> 0 | N25: ='Qtr Source Data'!Q17 -> -0.03
B26: Weighted avg shares, basic (000s) | C26: ='Qtr Source Data'!C18 -> 115407 | D26: n/a | E26: ='Qtr Source Data'!F18 -> 102343 | F26: ='Qtr Source Data'!G18 -> 102604 | G26: ='Qtr Source Data'!H18 -> 103723 | H26: n/a | I26: ='Qtr Source Data'!K18 -> 105159 | J26: ='Qtr Source Data'!L18 -> 106908 | K26: ='Qtr Source Data'!M18 -> 108450 | L26: n/a | M26: ='Qtr Source Data'!P18 -> 111726 | N26: ='Qtr Source Data'!Q18 -> 111422
B27: Weighted avg shares, diluted (000s) | C27: ='Qtr Source Data'!C19 -> 115407 | D27: n/a | E27: ='Qtr Source Data'!F19 -> 102343 | F27: ='Qtr Source Data'!G19 -> 102604 | G27: ='Qtr Source Data'!H19 -> 103723 | H27: n/a | I27: ='Qtr Source Data'!K19 -> 105159 | J27: ='Qtr Source Data'!L19 -> 106908 | K27: ='Qtr Source Data'!M19 -> 108450 | L27: n/a | M27: ='Qtr Source Data'!P19 -> 112130 | N27: ='Qtr Source Data'!Q19 -> 111422
A29: BALANCE SHEET (period end)
C30: Q3 2023 | D30: Q4 2023 | E30: Q1 2024 | F30: Q2 2024 | G30: Q3 2024 | H30: Q4 2024 | I30: Q1 2025 | J30: Q2 2025 | K30: Q3 2025 | L30: Q4 2025 | M30: Q1 2026 | N30: Q2 2026
B31: Cash and cash equivalents | C31: ='Qtr Source Data'!C24 -> 94419 | D31: ='Qtr Source Data'!D24 -> 135757 | E31: ='Qtr Source Data'!E24 -> 143747 | F31: ='Qtr Source Data'!F24 -> 133068 | G31: ='Qtr Source Data'!G24 -> 152073 | H31: ='Qtr Source Data'!H24 -> 161475 | I31: ='Qtr Source Data'!I24 -> 44105 | J31: ='Qtr Source Data'!J24 -> 36825 | ... N31: ='Qtr Source Data'!N24 -> 44623
B32: Short-term investments | C32: ='Qtr Source Data'!C25 -> 166841 | D32: ='Qtr Source Data'!D25 -> 194257 | E32: ='Qtr Source Data'!E25 -> 247013 | F32: ='Qtr Source Data'!F25 -> 212396 | G32: ='Qtr Source Data'!G25 -> 209003 | H32: ='Qtr Source Data'!H25 -> 154249 | I32: ='Qtr Source Data'!I25 -> 44188 | J32: ='Qtr Source Data'!J25 -> 48815 | ... N32: ='Qtr Source Data'!N25 -> 27691
B33: Accounts receivable, net | C33: ='Qtr Source Data'!C26 -> 30480 | D33: ='Qtr Source Data'!D26 -> 31404 | E33: ='Qtr Source Data'!E26 -> 24741 | F33: ='Qtr Source Data'!F26 -> 20964 | G33: ='Qtr Source Data'!G26 -> 23749 | H33: ='Qtr Source Data'!H26 -> 23641 | I33: ='Qtr Source Data'!I26 -> 28549 | J33: ='Qtr Source Data'!J26 -> 18055 | ... N33: ='Qtr Source Data'!N26 -> 10734
B34: Prepaid expenses | C34: ='Qtr Source Data'!C27 -> 30761 | D34: ='Qtr Source Data'!D27 -> 20980 | E34: ='Qtr Source Data'!E27 -> 20429 | F34: ='Qtr Source Data'!F27 -> 30841 | G34: ='Qtr Source Data'!G27 -> 24706 | H34: ='Qtr Source Data'!H27 -> 17100 | I34: ='Qtr Source Data'!I27 -> 14514 | J34: ='Qtr Source Data'!J27 -> 23683 | ... N34: ='Qtr Source Data'!N27 -> 11352
B35: Other current assets | C35: ='Qtr Source Data'!C28 -> 25195 | D35: ='Qtr Source Data'!D28 -> 32437 | E35: ='Qtr Source Data'!E28 -> 30010 | F35: ='Qtr Source Data'!F28 -> 36279 | G35: ='Qtr Source Data'!G28 -> 86980 | H35: ='Qtr Source Data'!H28 -> 81094 | I35: ='Qtr Source Data'!I28 -> 78395 | J35: ='Qtr Source Data'!J28 -> 76548 | ... N35: ='Qtr Source Data'!N28 -> 14301
B36: Total current assets | C36: =SUM(C31:C35) -> 347696 | D36: =SUM(D31:D35) -> 414835 | E36: =SUM(E31:E35) -> 465940 | F36: =SUM(F31:F35) -> 433548 | G36: =SUM(G31:G35) -> 496511 | H36: =SUM(H31:H35) -> 437559 | I36: =SUM(I31:I35) -> 209751 | J36: =SUM(J31:J35) -> 203926 | ... N36: =SUM(N31:N35) -> 108701
B37: Long-term investments | C37: ='Qtr Source Data'!C29 -> 412541 | D37: ='Qtr Source Data'!D29 -> 249547 | E37: ='Qtr Source Data'!E29 -> 221665 | F37: ='Qtr Source Data'!F29 -> 259925 | G37: ='Qtr Source Data'!G29 -> 270161 | H37: ='Qtr Source Data'!H29 -> 212650 | I37: ='Qtr Source Data'!I29 -> 38093 | J37: ='Qtr Source Data'!J29 -> 28474 | ... N37: ='Qtr Source Data'!N29 -> 0
B38: Property and equipment, net | C38: ='Qtr Source Data'!C30 -> 168735 | D38: ='Qtr Source Data'!D30 -> 183073 | E38: ='Qtr Source Data'!E30 -> 188430 | F38: ='Qtr Source Data'!F30 -> 179278 | G38: ='Qtr Source Data'!G30 -> 177882 | H38: ='Qtr Source Data'!H30 -> 170648 | I38: ='Qtr Source Data'!I30 -> 144971 | J38: ='Qtr Source Data'!J30 -> 135491 | ... N38: ='Qtr Source Data'!N30 -> 94948
B39: Goodwill | C39: ='Qtr Source Data'!C31 -> 617690 | D39: ='Qtr Source Data'!D31 -> 631995 | E39: ='Qtr Source Data'!E31 -> 628784 | F39: ='Qtr Source Data'!F31 -> 189769 | G39: ='Qtr Source Data'!G31 -> 0 | H39: ='Qtr Source Data'!H31 -> 0 | I39: ='Qtr Source Data'!I31 -> 0 | J39: ='Qtr Source Data'!J31 -> 0 | ... N39: ='Qtr Source Data'!N31 -> 0
B40: Intangible assets, net | C40: ='Qtr Source Data'!C32 -> 56638 | D40: ='Qtr Source Data'!D32 -> 52430 | E40: ='Qtr Source Data'!E32 -> 48143 | F40: ='Qtr Source Data'!F32 -> 12848 | G40: ='Qtr Source Data'!G32 -> 11424 | H40: ='Qtr Source Data'!H32 -> 10347 | I40: ='Qtr Source Data'!I32 -> 9271 | J40: ='Qtr Source Data'!J32 -> 8194 | ... N40: ='Qtr Source Data'!N32 -> 3957
B41: Right of use assets | C41: ='Qtr Source Data'!C33 -> 26568 | D41: ='Qtr Source Data'!D33 -> 25130 | E41: ='Qtr Source Data'!E33 -> 23521 | F41: ='Qtr Source Data'!F33 -> 21508 | G41: ='Qtr Source Data'!G33 -> 29071 | H41: ='Qtr Source Data'!H33 -> 22256 | I41: ='Qtr Source Data'!I33 -> 21479 | J41: ='Qtr Source Data'!J33 -> 19418 | ... N41: ='Qtr Source Data'!N33 -> 11505
B42: Deferred tax assets | C42: ='Qtr Source Data'!C34 -> 145807 | D42: ='Qtr Source Data'!D34 -> 141843 | E42: ='Qtr Source Data'!E34 -> 140200 | F42: ='Qtr Source Data'!F34 -> 2287 | G42: ='Qtr Source Data'!G34 -> 2308 | H42: ='Qtr Source Data'!H34 -> 0 | I42: ='Qtr Source Data'!I34 -> 0 | J42: ='Qtr Source Data'!J34 -> 0 | ... N42: ='Qtr Source Data'!N34 -> 0
B43: Other assets | C43: ='Qtr Source Data'!C35 -> 28964 | D43: ='Qtr Source Data'!D35 -> 28382 | E43: ='Qtr Source Data'!E35 -> 15961 | F43: ='Qtr Source Data'!F35 -> 15167 | G43: ='Qtr Source Data'!G35 -> 15315 | H43: ='Qtr Source Data'!H35 -> 15491 | I43: ='Qtr Source Data'!I35 -> 15204 | J43: ='Qtr Source Data'!J35 -> 8950 | ... N43: ='Qtr Source Data'!N35 -> 8514
B44: Total assets | C44: =C36+SUM(C37:C43) -> 1804639 | D44: =D36+SUM(D37:D43) -> 1727235 | E44: =E36+SUM(E37:E43) -> 1732644 | F44: =F36+SUM(F37:F43) -> 1114330 | G44: =G36+SUM(G37:G43) -> 1002672 | H44: =H36+SUM(H37:H43) -> 868951 | I44: =I36+SUM(I37:I43) -> 438769 | J44: =J36+SUM(J37:J43) -> 404453 | ... N44: =N36+SUM(N37:N43) -> 227625
B46: Accounts payable | C46: ='Qtr Source Data'!C36 -> 18187 | D46: ='Qtr Source Data'!D36 -> 28184 | E46: ='Qtr Source Data'!E36 -> 20119 | F46: ='Qtr Source Data'!F36 -> 14424 | G46: ='Qtr Source Data'!G36 -> 18124 | H46: ='Qtr Source Data'!H36 -> 15159 | I46: ='Qtr Source Data'!I36 -> 16812 | J46: ='Qtr Source Data'!J36 -> 8321 | ... N46: ='Qtr Source Data'!N36 -> 4775
B47: Deferred revenue | C47: ='Qtr Source Data'!C37 -> 58906 | D47: ='Qtr Source Data'!D37 -> 55336 | E47: ='Qtr Source Data'!E37 -> 54056 | F47: ='Qtr Source Data'!F37 -> 45023 | G47: ='Qtr Source Data'!G37 -> 44355 | H47: ='Qtr Source Data'!H37 -> 39217 | I47: ='Qtr Source Data'!I37 -> 45150 | J47: ='Qtr Source Data'!J37 -> 34759 | ... N47: ='Qtr Source Data'!N37 -> 26570
B48: Accrued liabilities | C48: ='Qtr Source Data'!C38 -> 73133 | D48: ='Qtr Source Data'!D38 -> 77863 | E48: ='Qtr Source Data'!E38 -> 73555 | F48: ='Qtr Source Data'!F38 -> 68001 | G48: ='Qtr Source Data'!G38 -> 125138 | H48: ='Qtr Source Data'!H38 -> 115360 | I48: ='Qtr Source Data'!I38 -> 109070 | J48: ='Qtr Source Data'!J38 -> 121373 | ... N48: ='Qtr Source Data'!N38 -> 27770
B49: Current portion of convertible senior notes, net | C49: ='Qtr Source Data'!C39 -> 0 | D49: ='Qtr Source Data'!D39 -> 357079 | E49: ='Qtr Source Data'!E39 -> 357458 | F49: ='Qtr Source Data'!F39 -> 357838 | G49: ='Qtr Source Data'!G39 -> 358222 | H49: ='Qtr Source Data'!H39 -> 358605 | I49: ='Qtr Source Data'!I39 -> 0 | J49: ='Qtr Source Data'!J39 -> 62516 | ... N49: ='Qtr Source Data'!N39 -> 33845
B50: Total current liabilities | C50: =SUM(C46:C49) -> 150226 | D50: =SUM(D46:D49) -> 518462 | E50: =SUM(E46:E49) -> 505188 | F50: =SUM(F46:F49) -> 485286 | G50: =SUM(G46:G49) -> 545839 | H50: =SUM(H46:H49) -> 528341 | I50: =SUM(I46:I49) -> 171032 | J50: =SUM(J46:J49) -> 226969 | ... N50: =SUM(N46:N49) -> 92960
B51: Convertible senior notes, net (long-term) | C51: ='Qtr Source Data'!C40 -> 599291 | D51: ='Qtr Source Data'!D40 -> 242758 | E51: ='Qtr Source Data'!E40 -> 242919 | F51: ='Qtr Source Data'!F40 -> 243079 | G51: ='Qtr Source Data'!G40 -> 243242 | H51: ='Qtr Source Data'!H40 -> 127344 | I51: ='Qtr Source Data'!I40 -> 62475 | J51: ='Qtr Source Data'!J40 -> 0 | ... N51: ='Qtr Source Data'!N40 -> 0
B52: Long-term operating lease liabilities | C52: ='Qtr Source Data'!C41 -> 19537 | D52: ='Qtr Source Data'!D41 -> 18063 | E52: ='Qtr Source Data'!E41 -> 16460 | F52: ='Qtr Source Data'!F41 -> 15595 | G52: ='Qtr Source Data'!G41 -> 23665 | H52: ='Qtr Source Data'!H41 -> 18509 | I52: ='Qtr Source Data'!I41 -> 17797 | J52: ='Qtr Source Data'!J41 -> 17700 | ... N52: ='Qtr Source Data'!N41 -> 12600
B53: Other long-term liabilities | C53: ='Qtr Source Data'!C42 -> 2236 | D53: ='Qtr Source Data'!D42 -> 3334 | E53: ='Qtr Source Data'!E42 -> 4603 | F53: ='Qtr Source Data'!F42 -> 4870 | G53: ='Qtr Source Data'!G42 -> 4945 | H53: ='Qtr Source Data'!H42 -> 1776 | I53: ='Qtr Source Data'!I42 -> 1794 | J53: ='Qtr Source Data'!J42 -> 1928 | ... N53: ='Qtr Source Data'!N42 -> 3451
B54: Total long-term liabilities | C54: =SUM(C51:C53) -> 621064 | D54: =SUM(D51:D53) -> 264155 | E54: =SUM(E51:E53) -> 263982 | F54: =SUM(F51:F53) -> 263544 | G54: =SUM(G51:G53) -> 271852 | H54: =SUM(H51:H53) -> 147629 | I54: =SUM(I51:I53) -> 82066 | J54: =SUM(J51:J53) -> 19628 | ... N54: =SUM(N51:N53) -> 16051
B55: Total liabilities | C55: =C50+C54 -> 771290 | D55: =D50+D54 -> 782617 | E55: =E50+E54 -> 769170 | F55: =F50+F54 -> 748830 | G55: =G50+G54 -> 817691 | H55: =H50+H54 -> 675970 | I55: =I50+I54 -> 253098 | J55: =J50+J54 -> 246597 | ... N55: =N50+N54 -> 109011
B57: Common stock (par) | C57: ='Qtr Source Data'!C43 -> 116 | D57: ='Qtr Source Data'!D43 -> 103 | E57: ='Qtr Source Data'!E43 -> 102 | F57: ='Qtr Source Data'!F43 -> 103 | G57: ='Qtr Source Data'!G43 -> 104 | H57: ='Qtr Source Data'!H43 -> 105 | I57: ='Qtr Source Data'!I43 -> 105 | J57: ='Qtr Source Data'!J43 -> 108 | ... N57: ='Qtr Source Data'!N43 -> 111
B58: Additional paid-in capital | C58: ='Qtr Source Data'!C44 -> 1151697 | D58: ='Qtr Source Data'!D44 -> 1031627 | E58: ='Qtr Source Data'!E44 -> 1057837 | F58: ='Qtr Source Data'!F44 -> 1075989 | G58: ='Qtr Source Data'!G44 -> 1098242 | H58: ='Qtr Source Data'!H44 -> 1114550 | I58: ='Qtr Source Data'!I44 -> 1125738 | J58: ='Qtr Source Data'!J44 -> 1133686 | ... N58: ='Qtr Source Data'!N44 -> 1148192
B59: Accumulated other comprehensive loss | C59: ='Qtr Source Data'!C45 -> -56426 | D59: ='Qtr Source Data'!D45 -> -34739 | E59: ='Qtr Source Data'!E45 -> -40672 | F59: ='Qtr Source Data'!F45 -> -39915 | G59: ='Qtr Source Data'!G45 -> -30049 | H59: ='Qtr Source Data'!H45 -> -32233 | I59: ='Qtr Source Data'!I45 -> -33247 | J59: ='Qtr Source Data'!J45 -> -33350 | ... N59: ='Qtr Source Data'!N45 -> -34104
B60: Accumulated deficit | C60: ='Qtr Source Data'!C46 -> -62038 | D60: ='Qtr Source Data'!D46 -> -52373 | E60: ='Qtr Source Data'!E46 -> -53793 | F60: ='Qtr Source Data'!F46 -> -670677 | G60: ='Qtr Source Data'!G46 -> -883316 | H60: ='Qtr Source Data'!H46 -> -889441 | I60: ='Qtr Source Data'!I46 -> -906925 | J60: ='Qtr Source Data'!J46 -> -942588 | ... N60: ='Qtr Source Data'!N46 -> -995585
B61: Total stockholders' equity | C61: =SUM(C57:C60) -> 1033349 | D61: =SUM(D57:D60) -> 944618 | E61: =SUM(E57:E60) -> 963474 | F61: =SUM(F57:F60) -> 365500 | G61: =SUM(G57:G60) -> 184981 | H61: =SUM(H57:H60) -> 192981 | I61: =SUM(I57:I60) -> 185671 | J61: =SUM(J57:J60) -> 157856 | ... N61: =SUM(N57:N60) -> 118614
B62: Total liabilities and stockholders' equity | C62: =C55+C61 -> 1804639 | D62: =D55+D61 -> 1727235 | E62: =E55+E61 -> 1732644 | F62: =F55+F61 -> 1114330 | G62: =G55+G61 -> 1002672 | H62: =H55+H61 -> 868951 | I62: =I55+I61 -> 438769 | J62: =J55+J61 -> 404453 | ... N62: =N55+N61 -> 227625
B63: Check: assets less liabilities and equity (should be 0) | C63: =C44-C62 -> 0 | D63: =D44-D62 -> 0 | E63: =E44-E62 -> 0 | F63: =F44-F62 -> 0 | G63: =G44-G62 -> 0 | H63: =H44-H62 -> 0 | I63: =I44-I62 -> 0 | J63: =J44-J62 -> 0 | ... N63: =N44-N62 -> 0
B64: Check: total assets vs as-reported (should be 0) | C64: =C44-'Qtr Source Data'!C47 -> 0 | D64: =D44-'Qtr Source Data'!D47 -> 0 | E64: =E44-'Qtr Source Data'!E47 -> 0 | F64: =F44-'Qtr Source Data'!F47 -> 0 | G64: =G44-'Qtr Source Data'!G47 -> 0 | H64: =H44-'Qtr Source Data'!H47 -> 0 | I64: =I44-'Qtr Source Data'!I47 -> 0 | J64: =J44-'Qtr Source Data'!J47 -> 0 | ... N64: =N44-'Qtr Source Data'!N47 -> 0
B66: Memo:
B67: Cash + short and long-term investments | C67: =C31+C32+C37 -> 673801 | D67: =D31+D32+D37 -> 579561 | E67: =E31+E32+E37 -> 612425 | F67: =F31+F32+F37 -> 605389 | G67: =G31+G32+G37 -> 631237 | H67: =H31+H32+H37 -> 528374 | I67: =I31+I32+I37 -> 126386 | J67: =J31+J32+J37 -> 114114 | ... N67: =N31+N32+N37 -> 72314
B68: Total convertible notes (current + long-term) | C68: =C49+C51 -> 599291 | D68: =D49+D51 -> 599837 | E68: =E49+E51 -> 600377 | F68: =F49+F51 -> 600917 | G68: =G49+G51 -> 601464 | H68: =H49+H51 -> 485949 | I68: =I49+I51 -> 62475 | J68: =J49+J51 -> 62516 | ... N68: =N49+N51 -> 33845
B69: Net cash (debt) | C69: =C67-C68 -> 74510 | D69: =D67-D68 -> -20276 | E69: =E67-E68 -> 12048 | F69: =F67-F68 -> 4472 | G69: =G67-G68 -> 29773 | H69: =H67-H68 -> 42425 | I69: =I67-I68 -> 63911 | J69: =J67-J68 -> 51598 | ... N69: =N67-N68 -> 38469
B70: Working capital (current assets less current liabilities) | C70: =C36-C50 -> 197470 | D70: =D36-D50 -> -103627 | E70: =E36-E50 -> -39248 | F70: =F36-F50 -> -51738 | G70: =G36-G50 -> -49328 | H70: =H36-H50 -> -90782 | I70: =I36-I50 -> 38719 | J70: =J36-J50 -> -23043 | ... N70: =N36-N50 -> 15741
A72: CASH FLOW STATEMENT (quarterly, derived from year-to-date filings)
C73: Q3 2023 | D73: Q4 2023 | E73: Q1 2024 | F73: Q2 2024 | G73: Q3 2024 | H73: Q4 2024 | I73: Q1 2025 | J73: Q2 2025 | K73: Q3 2025 | L73: Q4 2025 | M73: Q1 2026 | N73: Q2 2026 | O73: LTM
B74: Operating activities
B75: Net income (loss) | C75: ='Qtr Source Data'!D54-'Qtr Source Data'!C54 -> -18283 | D75: ='Qtr Source Data'!E54-'Qtr Source Data'!D54 -> 9665 | E75: ='Qtr Source Data'!F54 -> -1420 | F75: ='Qtr Source Data'!G54-'Qtr Source Data'!F54 -> -616884 | G75: ='Qtr Source Data'!H54-'Qtr Source Data'!G54 -> -212639 | H75: ='Qtr Source Data'!I54-'Qtr Source Data'!H54 -> -6125 | I75: ='Qtr Source Data'!J54 -> -17484 | J75: ='Qtr Source Data'!K54-'Qtr Source Data'!J54 -> -35663 | K75: ='Qtr Source Data'!L54-'Qtr Source Data'!K54 -> -17471 | L75: ='Qtr Source Data'!M54-'Qtr Source Data'!L54 -> -32803 | M75: ='Qtr Source Data'!N54 -> 228 | N75: ='Qtr Source Data'!O54-'Qtr Source Data'!N54 -> -2951 | O75: =SUM(K75:N75) -> -52997
B76: Share-based compensation expense | C76: ='Qtr Source Data'!D55-'Qtr Source Data'!C55 -> 31930 | D76: ='Qtr Source Data'!E55-'Qtr Source Data'!D55 -> 31906 | E76: ='Qtr Source Data'!F55 -> 29289 | F76: ='Qtr Source Data'!G55-'Qtr Source Data'!F55 -> 18047 | G76: ='Qtr Source Data'!H55-'Qtr Source Data'!G55 -> 21931 | H76: ='Qtr Source Data'!I55-'Qtr Source Data'!H55 -> 15347 | I76: ='Qtr Source Data'!J55 -> 11257 | J76: ='Qtr Source Data'!K55-'Qtr Source Data'!J55 -> 7912 | K76: ='Qtr Source Data'!L55-'Qtr Source Data'!K55 -> 5925 | L76: ='Qtr Source Data'!M55-'Qtr Source Data'!L55 -> 6770 | M76: ='Qtr Source Data'!N55 -> 2711 | N76: ='Qtr Source Data'!O55-'Qtr Source Data'!N55 -> 2324 | O76: =SUM(K76:N76) -> 17730
B77: Depreciation and amortization expense | C77: ='Qtr Source Data'!D56-'Qtr Source Data'!C56 -> 56918 | D77: ='Qtr Source Data'!E56-'Qtr Source Data'!D56 -> 20773 | E77: ='Qtr Source Data'!F56 -> 19687 | F77: ='Qtr Source Data'!G56-'Qtr Source Data'!F56 -> 19706 | G77: ='Qtr Source Data'!H56-'Qtr Source Data'!G56 -> 19573 | H77: ='Qtr Source Data'!I56-'Qtr Source Data'!H56 -> 19378 | I77: ='Qtr Source Data'!J56 -> 32094 | J77: ='Qtr Source Data'!K56-'Qtr Source Data'!J56 -> 16226 | K77: ='Qtr Source Data'!L56-'Qtr Source Data'!K56 -> 15321 | L77: ='Qtr Source Data'!M56-'Qtr Source Data'!L56 -> 14996 | M77: ='Qtr Source Data'!N56 -> 13947 | N77: ='Qtr Source Data'!O56-'Qtr Source Data'!N56 -> 13045 | O77: =SUM(K77:N77) -> 57309
B78: Deferred income taxes | C78: ='Qtr Source Data'!D57-'Qtr Source Data'!C57 -> 787 | D78: ='Qtr Source Data'!E57-'Qtr Source Data'!D57 -> 5646 | E78: ='Qtr Source Data'!F57 -> 2877 | F78: ='Qtr Source Data'!G57-'Qtr Source Data'!F57 -> 138155 | G78: ='Qtr Source Data'!H57-'Qtr Source Data'!G57 -> 71 | H78: ='Qtr Source Data'!I57-'Qtr Source Data'!H57 -> 2216 | I78: ='Qtr Source Data'!J57 -> 15 | J78: ='Qtr Source Data'!K57-'Qtr Source Data'!J57 -> 134 | K78: ='Qtr Source Data'!L57-'Qtr Source Data'!K57 -> 170 | L78: ='Qtr Source Data'!M57-'Qtr Source Data'!L57 -> 1029 | M78: ='Qtr Source Data'!N57 -> -95 | N78: ='Qtr Source Data'!O57-'Qtr Source Data'!N57 -> 84 | O78: =SUM(K78:N78) -> 1188
B79: Operating lease expense, net of accretion | C79: ='Qtr Source Data'!D58-'Qtr Source Data'!C58 -> 1526 | D79: ='Qtr Source Data'!E58-'Qtr Source Data'!D58 -> 1544 | E79: ='Qtr Source Data'!F58 -> 1567 | F79: ='Qtr Source Data'!G58-'Qtr Source Data'!F58 -> 1574 | G79: ='Qtr Source Data'!H58-'Qtr Source Data'!G58 -> 1506 | H79: ='Qtr Source Data'!I58-'Qtr Source Data'!H58 -> 1217 | I79: ='Qtr Source Data'!J58 -> 1089 | J79: ='Qtr Source Data'!K58-'Qtr Source Data'!J58 -> 930 | K79: ='Qtr Source Data'!L58-'Qtr Source Data'!K58 -> 864 | L79: ='Qtr Source Data'!M58-'Qtr Source Data'!L58 -> 758 | M79: ='Qtr Source Data'!N58 -> 545 | N79: ='Qtr Source Data'!O58-'Qtr Source Data'!N58 -> 531 | O79: =SUM(K79:N79) -> 2698
B80: Amortization of debt issuance costs | C80: ='Qtr Source Data'!D59-'Qtr Source Data'!C59 -> 622 | D80: ='Qtr Source Data'!E59-'Qtr Source Data'!D59 -> 546 | E80: ='Qtr Source Data'!F59 -> 541 | F80: ='Qtr Source Data'!G59-'Qtr Source Data'!F59 -> 540 | G80: ='Qtr Source Data'!H59-'Qtr Source Data'!G59 -> 547 | H80: ='Qtr Source Data'!I59-'Qtr Source Data'!H59 -> 519 | I80: ='Qtr Source Data'!J59 -> 377 | J80: ='Qtr Source Data'!K59-'Qtr Source Data'!J59 -> 41 | K80: ='Qtr Source Data'!L59-'Qtr Source Data'!K59 -> 41 | L80: ='Qtr Source Data'!M59-'Qtr Source Data'!L59 -> 41 | M80: ='Qtr Source Data'!N59 -> 31 | N80: ='Qtr Source Data'!O59-'Qtr Source Data'!N59 -> 22 | O80: =SUM(K80:N80) -> 135
B81: Loss from write-offs of property and equipment | C81: ='Qtr Source Data'!D60-'Qtr Source Data'!C60 -> 3128 | D81: ='Qtr Source Data'!E60-'Qtr Source Data'!D60 -> 559 | E81: ='Qtr Source Data'!F60 -> 478 | F81: ='Qtr Source Data'!G60-'Qtr Source Data'!F60 -> 1179 | G81: ='Qtr Source Data'!H60-'Qtr Source Data'!G60 -> 367 | H81: ='Qtr Source Data'!I60-'Qtr Source Data'!H60 -> 3771 | I81: ='Qtr Source Data'!J60 -> 2287 | J81: ='Qtr Source Data'!K60-'Qtr Source Data'!J60 -> -1729 | K81: ='Qtr Source Data'!L60-'Qtr Source Data'!K60 -> 235 | L81: ='Qtr Source Data'!M60-'Qtr Source Data'!L60 -> 1166 | M81: ='Qtr Source Data'!N60 -> 49 | N81: ='Qtr Source Data'!O60-'Qtr Source Data'!N60 -> -1 | O81: =SUM(K81:N81) -> 1449
B82: Gain on early extinguishment of debt | C82: ='Qtr Source Data'!D61-'Qtr Source Data'!C61 -> -32149 | D82: ='Qtr Source Data'!E61-'Qtr Source Data'!D61 -> 0 | E82: ='Qtr Source Data'!F61 -> 0 | F82: ='Qtr Source Data'!G61-'Qtr Source Data'!F61 -> 0 | G82: ='Qtr Source Data'!H61-'Qtr Source Data'!G61 -> 0 | H82: ='Qtr Source Data'!I61-'Qtr Source Data'!H61 -> -19515 | I82: ='Qtr Source Data'!J61 -> -7360 | J82: ='Qtr Source Data'!K61-'Qtr Source Data'!J61 -> 0 | K82: ='Qtr Source Data'!L61-'Qtr Source Data'!K61 -> 0 | L82: ='Qtr Source Data'!M61-'Qtr Source Data'!L61 -> -478 | M82: ='Qtr Source Data'!N61 -> -523 | N82: ='Qtr Source Data'!O61-'Qtr Source Data'!N61 -> 0 | O82: =SUM(K82:N82) -> -1001
B83: Realized (gain) loss on sale of investments | C83: ='Qtr Source Data'!D62-'Qtr Source Data'!C62 -> 0 | D83: ='Qtr Source Data'!E62-'Qtr Source Data'!D62 -> 2106 | E83: ='Qtr Source Data'!F62 -> 0 | F83: ='Qtr Source Data'!G62-'Qtr Source Data'!F62 -> 0 | G83: ='Qtr Source Data'!H62-'Qtr Source Data'!G62 -> 0 | H83: ='Qtr Source Data'!I62-'Qtr Source Data'!H62 -> 27 | I83: ='Qtr Source Data'!J62 -> -752 | J83: ='Qtr Source Data'!K62-'Qtr Source Data'!J62 -> 0 | K83: ='Qtr Source Data'!L62-'Qtr Source Data'!K62 -> 0 | L83: ='Qtr Source Data'!M62-'Qtr Source Data'!L62 -> 0 | M83: ='Qtr Source Data'!N62 -> -5 | N83: ='Qtr Source Data'!O62-'Qtr Source Data'!N62 -> 0 | O83: =SUM(K83:N83) -> -5
B84: Impairment expense | C84: ='Qtr Source Data'!D63-'Qtr Source Data'!C63 -> 3600 | D84: ='Qtr Source Data'!E63-'Qtr Source Data'!D63 -> 0 | E84: ='Qtr Source Data'!F63 -> 0 | F84: ='Qtr Source Data'!G63-'Qtr Source Data'!F63 -> 481531 | G84: ='Qtr Source Data'!H63-'Qtr Source Data'!G63 -> 195708 | H84: ='Qtr Source Data'!I63-'Qtr Source Data'!H63 -> 0 | I84: ='Qtr Source Data'!J63 -> 0 | J84: ='Qtr Source Data'!K63-'Qtr Source Data'!J63 -> 2000 | K84: ='Qtr Source Data'!L63-'Qtr Source Data'!K63 -> 0 | L84: ='Qtr Source Data'!M63-'Qtr Source Data'!L63 -> 0 | M84: ='Qtr Source Data'!N63 -> 0 | N84: ='Qtr Source Data'!O63-'Qtr Source Data'!N63 -> 0 | O84: =SUM(K84:N84) -> 0
B85: Impairment of lease related assets | C85: ='Qtr Source Data'!D64-'Qtr Source Data'!C64 -> 0 | D85: ='Qtr Source Data'!E64-'Qtr Source Data'!D64 -> 0 | E85: ='Qtr Source Data'!F64 -> 0 | F85: ='Qtr Source Data'!G64-'Qtr Source Data'!F64 -> 2189 | G85: ='Qtr Source Data'!H64-'Qtr Source Data'!G64 -> 0 | H85: ='Qtr Source Data'!I64-'Qtr Source Data'!H64 -> 3368 | I85: ='Qtr Source Data'!J64 -> 0 | J85: ='Qtr Source Data'!K64-'Qtr Source Data'!J64 -> 3004 | K85: ='Qtr Source Data'!L64-'Qtr Source Data'!K64 -> 0 | L85: ='Qtr Source Data'!M64-'Qtr Source Data'!L64 -> 4311 | M85: ='Qtr Source Data'!N64 -> 0 | N85: ='Qtr Source Data'!O64-'Qtr Source Data'!N64 -> 0 | O85: =SUM(K85:N85) -> 4311
B86: Impairment of strategic equity investment | C86: ='Qtr Source Data'!D65-'Qtr Source Data'!C65 -> 0 | D86: ='Qtr Source Data'!E65-'Qtr Source Data'!D65 -> 0 | E86: ='Qtr Source Data'!F65 -> 0 | F86: ='Qtr Source Data'!G65-'Qtr Source Data'!F65 -> 0 | G86: ='Qtr Source Data'!H65-'Qtr Source Data'!G65 -> 0 | H86: ='Qtr Source Data'!I65-'Qtr Source Data'!H65 -> 0 | I86: ='Qtr Source Data'!J65 -> 0 | J86: ='Qtr Source Data'!K65-'Qtr Source Data'!J65 -> 6000 | K86: ='Qtr Source Data'!L65-'Qtr Source Data'!K65 -> 0 | L86: ='Qtr Source Data'!M65-'Qtr Source Data'!L65 -> 0 | M86: ='Qtr Source Data'!N65 -> 0 | N86: ='Qtr Source Data'!O65-'Qtr Source Data'!N65 -> 0 | O86: =SUM(K86:N86) -> 0
... B95: Change in other liabilities | C95: ='Qtr Source Data'!D74-'Qtr Source Data'!C74 -> -1605 | D95: ='Qtr Source Data'!E74-'Qtr Source Data'!D74 -> -1527 | E95: ='Qtr Source Data'!F74 -> -1580 | F95: ='Qtr Source Data'!G74-'Qtr Source Data'!F74 -> -1300 | G95: ='Qtr Source Data'!H74-'Qtr Source Data'!G74 -> -88 | H95: ='Qtr Source Data'!I74-'Qtr Source Data'!H74 -> -4817 | I95: ='Qtr Source Data'!J74 -> -752 | J95: ='Qtr Source Data'!K74-'Qtr Source Data'!J74 -> -770 | K95: ='Qtr Source Data'!L74-'Qtr Source Data'!K74 -> -1755 | L95: ='Qtr Source Data'!M74-'Qtr Source Data'!L74 -> 1321 | M95: ='Qtr Source Data'!N74 -> -841 | N95: ='Qtr Source Data'!O74-'Qtr Source Data'!N74 -> 19 | O95: =SUM(K95:N95) -> -1256
B96: Net cash from operating activities | C96: =SUM(C75:C95) -> 32807 | D96: =SUM(D75:D95) -> 77484 | E96: =SUM(E75:E95) -> 53318 | F96: =SUM(F75:F95) -> 14227 | G96: =SUM(G75:G95) -> 39532 | H96: =SUM(H75:H95) -> 18128 | I96: =SUM(I75:I95) -> 24526 | J96: =SUM(J75:J95) -> -4840 | ... O96: =SUM(O75:O95) -> 9965
B98: Investing activities
B99: Purchases of property and equipment | C99: ='Qtr Source Data'!D75-'Qtr Source Data'!C75 -> -23434 | D99: ='Qtr Source Data'!E75-'Qtr Source Data'!D75 -> -25754 | E99: ='Qtr Source Data'!F75 -> -28017 | F99: ='Qtr Source Data'!G75-'Qtr Source Data'!F75 -> -17800 | G99: ='Qtr Source Data'!H75-'Qtr Source Data'!G75 -> -15842 | H99: ='Qtr Source Data'!I75-'Qtr Source Data'!H75 -> -13294 | I99: ='Qtr Source Data'!J75 -> -8665 | J99: ='Qtr Source Data'!K75-'Qtr Source Data'!J75 -> -7230 | K99: ='Qtr Source Data'!L75-'Qtr Source Data'!K75 -> -5756 | L99: ='Qtr Source Data'!M75-'Qtr Source Data'!L75 -> -6472 | M99: ='Qtr Source Data'!N75 -> -1042 | N99: ='Qtr Source Data'!O75-'Qtr Source Data'!N75 -> -3658 | O99: =SUM(K99:N99) -> -16928
B100: Proceeds from disposition of textbooks | C100: ='Qtr Source Data'!D76-'Qtr Source Data'!C76 -> 0 | D100: ='Qtr Source Data'!E76-'Qtr Source Data'!D76 -> 0 | E100: ='Qtr Source Data'!F76 -> 0 | F100: ='Qtr Source Data'!G76-'Qtr Source Data'!F76 -> 0 | G100: ='Qtr Source Data'!H76-'Qtr Source Data'!G76 -> 0 | H100: ='Qtr Source Data'!I76-'Qtr Source Data'!H76 -> 0 | I100: ='Qtr Source Data'!J76 -> 0 | J100: ='Qtr Source Data'!K76-'Qtr Source Data'!J76 -> 0 | K100: ='Qtr Source Data'!L76-'Qtr Source Data'!K76 -> 0 | L100: ='Qtr Source Data'!M76-'Qtr Source Data'!L76 -> 0 | M100: ='Qtr Source Data'!N76 -> 0 | N100: ='Qtr Source Data'!O76-'Qtr Source Data'!N76 -> 0 | O100: =SUM(K100:N100) -> 0
B101: Purchases of investments | C101: ='Qtr Source Data'!D77-'Qtr Source Data'!C77 -> -32866 | D101: ='Qtr Source Data'!E77-'Qtr Source Data'!D77 -> -52664 | E101: ='Qtr Source Data'!F77 -> -79028 | F101: ='Qtr Source Data'!G77-'Qtr Source Data'!F77 -> -44641 | G101: ='Qtr Source Data'!H77-'Qtr Source Data'!G77 -> -10544 | H101: ='Qtr Source Data'!I77-'Qtr Source Data'!H77 -> -36737 | I101: ='Qtr Source Data'!J77 -> -793 | J101: ='Qtr Source Data'!K77-'Qtr Source Data'!J77 -> 0 | K101: ='Qtr Source Data'!L77-'Qtr Source Data'!K77 -> 0 | L101: ='Qtr Source Data'!M77-'Qtr Source Data'!L77 -> 0 | M101: ='Qtr Source Data'!N77 -> 0 | N101: ='Qtr Source Data'!O77-'Qtr Source Data'!N77 -> 0 | O101: =SUM(K101:N101) -> 0
B102: Maturities of investments | C102: ='Qtr Source Data'!D78-'Qtr Source Data'!C78 -> 84335 | D102: ='Qtr Source Data'!E78-'Qtr Source Data'!D78 -> 36000 | E102: ='Qtr Source Data'!F78 -> 50731 | F102: ='Qtr Source Data'!G78-'Qtr Source Data'!F78 -> 39159 | G102: ='Qtr Source Data'!H78-'Qtr Source Data'!G78 -> 7017 | H102: ='Qtr Source Data'!I78-'Qtr Source Data'!H78 -> 74764 | I102: ='Qtr Source Data'!J78 -> 103214 | J102: ='Qtr Source Data'!K78-'Qtr Source Data'!J78 -> 4496 | K102: ='Qtr Source Data'!L78-'Qtr Source Data'!K78 -> 3414 | L102: ='Qtr Source Data'!M78-'Qtr Source Data'!L78 -> 18931 | M102: ='Qtr Source Data'!N78 -> 13477 | N102: ='Qtr Source Data'!O78-'Qtr Source Data'!N78 -> 6554 | O102: =SUM(K102:N102) -> 42376
B103: Proceeds from sale of investments | C103: ='Qtr Source Data'!D79-'Qtr Source Data'!C79 -> 0 | D103: ='Qtr Source Data'!E79-'Qtr Source Data'!D79 -> 155852 | E103: ='Qtr Source Data'!F79 -> 0 | F103: ='Qtr Source Data'!G79-'Qtr Source Data'!F79 -> 0 | G103: ='Qtr Source Data'!H79-'Qtr Source Data'!G79 -> 0 | H103: ='Qtr Source Data'!I79-'Qtr Source Data'!H79 -> 70077 | I103: ='Qtr Source Data'!J79 -> 181158 | J103: ='Qtr Source Data'!K79-'Qtr Source Data'!J79 -> 0 | K103: ='Qtr Source Data'!L79-'Qtr Source Data'!K79 -> 0 | L103: ='Qtr Source Data'!M79-'Qtr Source Data'!L79 -> 0 | M103: ='Qtr Source Data'!N79 -> 5679 | N103: ='Qtr Source Data'!O79-'Qtr Source Data'!N79 -> 0 | O103: =SUM(K103:N103) -> 5679
B104: Proceeds from sale of strategic equity investment | C104: ='Qtr Source Data'!D80-'Qtr Source Data'!C80 -> 0 | D104: ='Qtr Source Data'!E80-'Qtr Source Data'!D80 -> 0 | E104: ='Qtr Source Data'!F80 -> 15500 | F104: ='Qtr Source Data'!G80-'Qtr Source Data'!F80 -> 0 | G104: ='Qtr Source Data'!H80-'Qtr Source Data'!G80 -> 0 | H104: ='Qtr Source Data'!I80-'Qtr Source Data'!H80 -> 0 | I104: ='Qtr Source Data'!J80 -> 0 | J104: ='Qtr Source Data'!K80-'Qtr Source Data'!J80 -> 0 | K104: ='Qtr Source Data'!L80-'Qtr Source Data'!K80 -> 0 | L104: ='Qtr Source Data'!M80-'Qtr Source Data'!L80 -> 0 | M104: ='Qtr Source Data'!N80 -> 0 | N104: ='Qtr Source Data'!O80-'Qtr Source Data'!N80 -> 0 | O104: =SUM(K104:N104) -> 0
B105: Purchase of strategic equity investment | C105: ='Qtr Source Data'!D81-'Qtr Source Data'!C81 -> -2249 | D105: ='Qtr Source Data'!E81-'Qtr Source Data'!D81 -> 0 | E105: ='Qtr Source Data'!F81 -> 0 | F105: ='Qtr Source Data'!G81-'Qtr Source Data'!F81 -> 0 | G105: ='Qtr Source Data'!H81-'Qtr Source Data'!G81 -> 0 | H105: ='Qtr Source Data'!I81-'Qtr Source Data'!H81 -> 0 | I105: ='Qtr Source Data'!J81 -> 0 | J105: ='Qtr Source Data'!K81-'Qtr Source Data'!J81 -> 0 | K105: ='Qtr Source Data'!L81-'Qtr Source Data'!K81 -> 0 | L105: ='Qtr Source Data'!M81-'Qtr Source Data'!L81 -> 0 | M105: ='Qtr Source Data'!N81 -> 0 | N105: ='Qtr Source Data'!O81-'Qtr Source Data'!N81 -> 0 | O105: =SUM(K105:N105) -> 0
B106: Net cash from investing activities | C106: =SUM(C99:C105) -> 25786 | D106: =SUM(D99:D105) -> 113434 | E106: =SUM(E99:E105) -> -40814 | F106: =SUM(F99:F105) -> -23282 | G106: =SUM(G99:G105) -> -19369 | H106: =SUM(H99:H105) -> 94810 | I106: =SUM(I99:I105) -> 274914 | J106: =SUM(J99:J105) -> -2734 | ... O106: =SUM(O99:O105) -> 31127
B108: Financing activities
B109: Proceeds from common stock issued under stock plans | C109: ='Qtr Source Data'!D82-'Qtr Source Data'!C82 -> 27 | D109: ='Qtr Source Data'!E82-'Qtr Source Data'!D82 -> 1057 | E109: ='Qtr Source Data'!F82 -> 0 | F109: ='Qtr Source Data'!G82-'Qtr Source Data'!F82 -> 2190 | G109: ='Qtr Source Data'!H82-'Qtr Source Data'!G82 -> 1 | H109: ='Qtr Source Data'!I82-'Qtr Source Data'!H82 -> 445 | I109: ='Qtr Source Data'!J82 -> 0 | J109: ='Qtr Source Data'!K82-'Qtr Source Data'!J82 -> 391 | K109: ='Qtr Source Data'!L82-'Qtr Source Data'!K82 -> 1 | L109: ='Qtr Source Data'!M82-'Qtr Source Data'!L82 -> 198 | M109: ='Qtr Source Data'!N82 -> 0 | N109: ='Qtr Source Data'!O82-'Qtr Source Data'!N82 -> 68 | O109: =SUM(K109:N109) -> 267
B110: Taxes paid on net share settlement of equity awards | C110: ='Qtr Source Data'!D83-'Qtr Source Data'!C83 -> -2789 | D110: ='Qtr Source Data'!E83-'Qtr Source Data'!D83 -> -2583 | E110: ='Qtr Source Data'!F83 -> -4294 | F110: ='Qtr Source Data'!G83-'Qtr Source Data'!F83 -> -3531 | G110: ='Qtr Source Data'!H83-'Qtr Source Data'!G83 -> -823 | H110: ='Qtr Source Data'!I83-'Qtr Source Data'!H83 -> -591 | I110: ='Qtr Source Data'!J83 -> -469 | J110: ='Qtr Source Data'!K83-'Qtr Source Data'!J83 -> -568 | K110: ='Qtr Source Data'!L83-'Qtr Source Data'!K83 -> -605 | L110: ='Qtr Source Data'!M83-'Qtr Source Data'!L83 -> -958 | M110: ='Qtr Source Data'!N83 -> -597 | N110: ='Qtr Source Data'!O83-'Qtr Source Data'!N83 -> -177 | O110: =SUM(K110:N110) -> -2337
B111: Payment of withholding tax | C111: ='Qtr Source Data'!D84-'Qtr Source Data'!C84 -> 0 | D111: ='Qtr Source Data'!E84-'Qtr Source Data'!D84 -> 0 | E111: ='Qtr Source Data'!F84 -> 0 | F111: ='Qtr Source Data'!G84-'Qtr Source Data'!F84 -> 0 | G111: ='Qtr Source Data'!H84-'Qtr Source Data'!G84 -> 0 | H111: ='Qtr Source Data'!I84-'Qtr Source Data'!H84 -> -3450 | I111: ='Qtr Source Data'!J84 -> 0 | J111: ='Qtr Source Data'!K84-'Qtr Source Data'!J84 -> 0 | K111: ='Qtr Source Data'!L84-'Qtr Source Data'!K84 -> 0 | L111: ='Qtr Source Data'!M84-'Qtr Source Data'!L84 -> -1621 | M111: ='Qtr Source Data'!N84 -> 0 | N111: ='Qtr Source Data'!O84-'Qtr Source Data'!N84 -> 0 | O111: =SUM(K111:N111) -> -1621
B112: Repurchase of common stock | C112: ='Qtr Source Data'!D85-'Qtr Source Data'!C85 -> 0 | D112: ='Qtr Source Data'!E85-'Qtr Source Data'!D85 -> -148438 | E112: ='Qtr Source Data'!F85 -> 0 | F112: ='Qtr Source Data'!G85-'Qtr Source Data'!F85 -> 0 | G112: ='Qtr Source Data'!H85-'Qtr Source Data'!G85 -> 0 | H112: ='Qtr Source Data'!I85-'Qtr Source Data'!H85 -> -2569 | I112: ='Qtr Source Data'!J85 -> 0 | J112: ='Qtr Source Data'!K85-'Qtr Source Data'!J85 -> 0 | K112: ='Qtr Source Data'!L85-'Qtr Source Data'!K85 -> 0 | L112: ='Qtr Source Data'!M85-'Qtr Source Data'!L85 -> 0 | M112: ='Qtr Source Data'!N85 -> 0 | N112: ='Qtr Source Data'!O85-'Qtr Source Data'!N85 -> -1721 | O112: =SUM(K112:N112) -> -1721
B113: Repayment of convertible senior notes | C113: ='Qtr Source Data'!D86-'Qtr Source Data'!C86 -> -136225 | D113: ='Qtr Source Data'!E86-'Qtr Source Data'!D86 -> 0 | E113: ='Qtr Source Data'!F86 -> 0 | F113: ='Qtr Source Data'!G86-'Qtr Source Data'!F86 -> 0 | G113: ='Qtr Source Data'!H86-'Qtr Source Data'!G86 -> 0 | H113: ='Qtr Source Data'!I86-'Qtr Source Data'!H86 -> -96520 | I113: ='Qtr Source Data'!J86 -> -416492 | J113: ='Qtr Source Data'!K86-'Qtr Source Data'!J86 -> 0 | K113: ='Qtr Source Data'!L86-'Qtr Source Data'!K86 -> 0 | L113: ='Qtr Source Data'!M86-'Qtr Source Data'!L86 -> -8356 | M113: ='Qtr Source Data'!N86 -> -19450 | N113: ='Qtr Source Data'!O86-'Qtr Source Data'!N86 -> 0 | O113: =SUM(K113:N113) -> -27806
B114: Proceeds from capped call | C114: ='Qtr Source Data'!D87-'Qtr Source Data'!C87 -> 0 | D114: ='Qtr Source Data'!E87-'Qtr Source Data'!D87 -> 0 | E114: ='Qtr Source Data'!F87 -> 0 | F114: ='Qtr Source Data'!G87-'Qtr Source Data'!F87 -> 0 | G114: ='Qtr Source Data'!H87-'Qtr Source Data'!G87 -> 0 | H114: ='Qtr Source Data'!I87-'Qtr Source Data'!H87 -> 0 | I114: ='Qtr Source Data'!J87 -> 0 | J114: ='Qtr Source Data'!K87-'Qtr Source Data'!J87 -> 0 | K114: ='Qtr Source Data'!L87-'Qtr Source Data'!K87 -> 0 | L114: ='Qtr Source Data'!M87-'Qtr Source Data'!L87 -> 0 | M114: ='Qtr Source Data'!N87 -> 0 | N114: ='Qtr Source Data'!O87-'Qtr Source Data'!N87 -> 0 | O114: =SUM(K114:N114) -> 0
B115: Net cash from financing activities | C115: =SUM(C109:C114) -> -138987 | D115: =SUM(D109:D114) -> -149964 | E115: =SUM(E109:E114) -> -4294 | F115: =SUM(F109:F114) -> -1341 | G115: =SUM(G109:G114) -> -822 | H115: =SUM(H109:H114) -> -102685 | I115: =SUM(I109:I114) -> -416961 | J115: =SUM(J109:J114) -> -177 | ... O115: =SUM(O109:O114) -> -33218
B117: Effect of exchange rate changes | C117: ='Qtr Source Data'!D88-'Qtr Source Data'!C88 -> -576 | D117: ='Qtr Source Data'!E88-'Qtr Source Data'!D88 -> 400 | E117: ='Qtr Source Data'!F88 -> -226 | F117: ='Qtr Source Data'!G88-'Qtr Source Data'!F88 -> -79 | G117: ='Qtr Source Data'!H88-'Qtr Source Data'!G88 -> 156 | H117: ='Qtr Source Data'!I88-'Qtr Source Data'!H88 -> -876 | I117: ='Qtr Source Data'!J88 -> 218 | J117: ='Qtr Source Data'!K88-'Qtr Source Data'!J88 -> 273 | K117: ='Qtr Source Data'!L88-'Qtr Source Data'!K88 -> -651 | L117: ='Qtr Source Data'!M88-'Qtr Source Data'!L88 -> -96 | M117: ='Qtr Source Data'!N88 -> -418 | N117: ='Qtr Source Data'!O88-'Qtr Source Data'!N88 -> -33 | O117: =SUM(K117:N117) -> -1198
...

Sheet Assumptions
A1: Assumptions & Inputs
A3: COMPANY
B4: Company name | C4: Chegg, Inc.
B5: Ticker | C5: #VALUE!
B6: Current share price ($) | C6: {=_FV(C5,"Price")} -> 0.72
B7: Shares outstanding (millions) | C7: {=(_FV(C5,"Shares outstanding",TRUE)+10322706)/1000000} -> 121.35021
B8: Market capitalization ($mm) | C8: =C6*C7 -> 87.372148
A10: FREE CASH FLOW & GROWTH
B11: CFO | C11: 14.161
B12: Minus CapEx | C12: -4.7
B13: Minus SBC | C13: -5.035
B14: Current normalized FCF | C14: =SUM(C11:C13) -> 4.426
B15: Current normalized FCF per share ($) | C15: {=SUM(C11:C13/C7)*2} -> 0.0729459
B16: Conservative case — annual FCF growth, Yrs 1-10 | C16: 0 | D16: Book's worst-realistic-case default: results never improve from here
B17: Moderate case — annual FCF growth, Yrs 1-10 | C17: 0.1 | D17: A modest, non-heroic growth assumption (still meant to be defensible, not optimistic)
B18: Terminal growth rate (in perpetuity after Yr 10) | C18: 0 | D18: 0% is the conservative default
A20: DISCOUNT RATE
B21: Current risk-free rate | C21: 0.04965 | D21: 10-yr Treasury yield
B22: Discount rate — Low | C22: 0.1
B23: Discount rate — Base | C23: =C21+(2*(0.0414)) -> 0.13245 | D23: WACC (CAPM)
B24: Discount rate — High | C24: 0.15
A26: BALANCE SHEET, $ MILLIONS
B27: Cash & equivalents | C27: 44.623
B28: Marketable securities (at market) | C28: 27.691
B29: Accounts receivable | C29: 10.734
B30: Inventory | C30: 0
B31: Other current assets | C31: =14.301+11.352 -> 25.653
B32: Net PP&E (book value) | C32: 94.948
B33: Total current liabilities | C33: 92.96
B34: Long-term debt | C34: 0
B35: Other long-term liabilities | C35: 16.051
B36: Off-balance-sheet / contingent liabilities | C36: 0 | D36: Underfunded pensions, environmental or lease exposure
A38: LIQUIDATION RECOVERY ASSUMPTIONS
B39: Securities — transaction cost % | C39: 0.02
B40: Receivables recovery — orderly liquidation | C40: 0.9
B41: Receivables recovery — fire sale | C41: 0.7
B42: Inventory recovery — orderly liquidation | C42: 0.7
B43: Inventory recovery — fire sale | C43: 0.4
B44: PP&E — estimated liquidation value ($mm) | C44: =C32*0.01 -> 0.94948 | D44: This is the hardest line to estimate and genuinely case-by-case
A46: COMPARABLE MULTIPLES
B47: Subject company pretax cash flow ($mm) | C47: 49.2
C48: EV/EBITDA column is the one the Market Multiples tab applies to pretax cash flow.
B49: Comparable name | C49: EV/EBITDA (x) | D49: Type | E49: P/E (x) | F49: P/B (x) | G49: EV/EBIT (x) | H49: EV/Revenue (x) | I49: Source / as-of
B50: Coursera/Udemy deal (EV ~$930M / Udemy FY25 Adj. EBITDA $63.5M) | C50: 14.6 | D50: Transaction | E50: =930/3.8 -> 244.73684 | H50: =930/789.8 -> 1.1775133 | I50: P/E = $930mm / Udemy FY25 net income $3.8mm (Udemy 10-K FY2025). EV/Rev = $930mm / FY25 revenue $789.8mm (Class Central, Apr 2026). P/B and EV/EBIT not sourced yet. $930mm was the announced equity value, not EV; Coursera recorded $673.6mm at close (May 11, 2026).
B51: Grand Canyon Education (LOPE) EV/EBITDA (TTM) | C51: 10.3 | D51: Trading | E51: 18.32 | F51: 5.85 | G51: 11.74 | H51: 3.26 | I51: stockanalysis.com (S&P Global data), price at Sep 18, 2026 close. Same source shows EV/EBITDA of 10.38x.
B52: Stride (LRN) EV/EBITDA (LTM) | C52: 6 | D52: Trading | E52: 11.05 | F52: 1.99 | G52: 6.12 | H52: 1.1 | I52: stockanalysis.com (S&P Global data), price at Sep 18, 2026 close. Same source shows EV/EBITDA of 5.41x.
B55: Median, all comps | C55: =IFERROR(MEDIAN(C50:C54),"") -> 10.3 | E55: =IFERROR(MEDIAN(E50:E54),"") -> 18.32 | F55: =IFERROR(MEDIAN(F50:F54),"") -> 3.92 | G55: =IFERROR(MEDIAN(G50:G54),"") -> 8.93 | H55: =IFERROR(MEDIAN(H50:H54),"") -> 1.1775133
B56: Average, Trading comps only | C56: =IFERROR(AVERAGEIF($D$50:$D$54,"Trading",C50:C54),"") -> 8.15 | E56: =IFERROR(AVERAGEIF($D$50:$D$54,"Trading",E50:E54),"") -> 14.685 | F56: =IFERROR(AVERAGEIF($D$50:$D$54,"Trading",F50:F54),"") -> 3.92 | G56: =IFERROR(AVERAGEIF($D$50:$D$54,"Trading",G50:G54),"") -> 8.93 | H56: =IFERROR(AVERAGEIF($D$50:$D$54,"Trading",H50:H54),"") -> 2.18
B57: Chegg at current price (LTM to Jun 30, 2026), for reference | C57: =IF('Quarterly Financials'!O124<=0,"n/m",(Assumptions!$C$8+('Quarterly Financials'!N68-'Quarterly Financials'!N67)/1000)/('Quarterly Financials'!O124/1000)) -> 28.749646 | E57: =IF('Quarterly Financials'!O22<=0,"n/m",Assumptions!$C$8/('Quarterly Financials'!O22/1000)) -> n/m | F57: =IF('Quarterly Financials'!N61<=0,"n/m",Assumptions!$C$8/('Quarterly Financials'!N61/1000)) -> 0.73660907 | G57: =IF('Quarterly Financials'!O16<=0,"n/m",(Assumptions!$C$8+('Quarterly Financials'!N68-'Quarterly Financials'!N67)/1000)/('Quarterly Financials'!O16/1000)) -> n/m | H57: =(Assumptions!$C$8+('Quarterly Financials'!N68-'Quarterly Financials'!N67)/1000)/('Quarterly Financials'!O6/1000) -> 0.18418432 | I57: Market cap from C8. EV adds convertible notes and subtracts cash and investments at Jun 30, 2026. "n/m" where the denominator is negative.
B59: "Type" must read exactly Transaction (private-market / M&A multiples) or Trading (public comps)
B60: Rows 53 to 54 are open for more comps. The medians, averages, and Market Multiples tab all pick them up automatically.
A62: MARGIN OF SAFETY
B63: Required margin of safety (discount to low-end value) | C63: 0.33

Sheet DCF NPV
A1: NPV / Discounted Cash Flow Analysis
B3: Company: | C3: =Assumptions!C4 -> Chegg, Inc.
A5: CONSERVATIVE CASE
C6: Year 1 | D6: Year 2 | E6: Year 3 | F6: Year 4 | G6: Year 5 | H6: Year 6 | I6: Year 7 | J6: Year 8 | K6: Year 9 | L6: Year 10
B7: FCF | C7: =Assumptions!$C$14*(1+Assumptions!$C$16)^(COLUMN()-2) -> 4.426 | D7: =Assumptions!$C$14*(1+Assumptions!$C$16)^(COLUMN()-2) -> 4.426 | E7: =Assumptions!$C$14*(1+Assumptions!$C$16)^(COLUMN()-2) -> 4.426 | F7: =Assumptions!$C$14*(1+Assumptions!$C$16)^(COLUMN()-2) -> 4.426 | G7: =Assumptions!$C$14*(1+Assumptions!$C$16)^(COLUMN()-2) -> 4.426 | H7: =Assumptions!$C$14*(1+Assumptions!$C$16)^(COLUMN()-2) -> 4.426 | I7: =Assumptions!$C$14*(1+Assumptions!$C$16)^(COLUMN()-2) -> 4.426 | J7: =Assumptions!$C$14*(1+Assumptions!$C$16)^(COLUMN()-2) -> 4.426 | ... L7: =Assumptions!$C$14*(1+Assumptions!$C$16)^(COLUMN()-2) -> 4.426
B8: FCF per share | C8: =Assumptions!$C$15*(1+Assumptions!$C$16)^(COLUMN()-2) -> 0.0729459 | D8: =Assumptions!$C$15*(1+Assumptions!$C$16)^(COLUMN()-2) -> 0.0729459 | E8: =Assumptions!$C$15*(1+Assumptions!$C$16)^(COLUMN()-2) -> 0.0729459 | F8: =Assumptions!$C$15*(1+Assumptions!$C$16)^(COLUMN()-2) -> 0.0729459 | G8: =Assumptions!$C$15*(1+Assumptions!$C$16)^(COLUMN()-2) -> 0.0729459 | H8: =Assumptions!$C$15*(1+Assumptions!$C$16)^(COLUMN()-2) -> 0.0729459 | I8: =Assumptions!$C$15*(1+Assumptions!$C$16)^(COLUMN()-2) -> 0.0729459 | J8: =Assumptions!$C$15*(1+Assumptions!$C$16)^(COLUMN()-2) -> 0.0729459 | ... L8: =Assumptions!$C$15*(1+Assumptions!$C$16)^(COLUMN()-2) -> 0.0729459
A10: MODERATE CASE
C11: Year 1 | D11: Year 2 | E11: Year 3 | F11: Year 4 | G11: Year 5 | H11: Year 6 | I11: Year 7 | J11: Year 8 | K11: Year 9 | L11: Year 10
B12: FCF | C12: =Assumptions!$C$14*(1+Assumptions!$C$17)^(COLUMN()-2) -> 4.8686 | D12: =Assumptions!$C$14*(1+Assumptions!$C$17)^(COLUMN()-2) -> 5.35546 | E12: =Assumptions!$C$14*(1+Assumptions!$C$17)^(COLUMN()-2) -> 5.891006 | F12: =Assumptions!$C$14*(1+Assumptions!$C$17)^(COLUMN()-2) -> 6.4801066 | G12: =Assumptions!$C$14*(1+Assumptions!$C$17)^(COLUMN()-2) -> 7.1281173 | H12: =Assumptions!$C$14*(1+Assumptions!$C$17)^(COLUMN()-2) -> 7.840929 | I12: =Assumptions!$C$14*(1+Assumptions!$C$17)^(COLUMN()-2) -> 8.6250219 | J12: =Assumptions!$C$14*(1+Assumptions!$C$17)^(COLUMN()-2) -> 9.4875241 | ... L12: =Assumptions!$C$14*(1+Assumptions!$C$17)^(COLUMN()-2) -> 11.479904
B13: FCF per share | C13: =Assumptions!$C$15*(1+Assumptions!$C$17)^(COLUMN()-2) -> 0.08024049 | D13: =Assumptions!$C$15*(1+Assumptions!$C$17)^(COLUMN()-2) -> 0.088264539 | E13: =Assumptions!$C$15*(1+Assumptions!$C$17)^(COLUMN()-2) -> 0.097090993 | F13: =Assumptions!$C$15*(1+Assumptions!$C$17)^(COLUMN()-2) -> 0.10680009 | G13: =Assumptions!$C$15*(1+Assumptions!$C$17)^(COLUMN()-2) -> 0.1174801 | H13: =Assumptions!$C$15*(1+Assumptions!$C$17)^(COLUMN()-2) -> 0.12922811 | I13: =Assumptions!$C$15*(1+Assumptions!$C$17)^(COLUMN()-2) -> 0.14215092 | J13: =Assumptions!$C$15*(1+Assumptions!$C$17)^(COLUMN()-2) -> 0.15636602 | ... L13: =Assumptions!$C$15*(1+Assumptions!$C$17)^(COLUMN()-2) -> 0.18920288
A15: CONSERVATIVE CASE
B16: Discount Rate | C16: Rate | D16: PV of Yrs 1-10 FCF | E16: Terminal Value (Yr 10) | F16: PV of Terminal Value | G16: Total NPV / Share
B17: Low | C17: =Assumptions!C22 -> 0.1 | D17: =NPV(C17,C8:L8) -> 0.44822098 | E17: =L8*(1+Assumptions!$C$18)/(C17-Assumptions!$C$18) -> 0.729459 | F17: =E17/(1+C17)^10 -> 0.28123802 | G17: =D17+F17 -> 0.729459
B18: Base | C18: =Assumptions!C23 -> 0.13245 | D18: =NPV(C18,C8:L8) -> 0.39197653 | E18: =L8*(1+Assumptions!$C$18)/(C18-Assumptions!$C$18) -> 0.55074292 | F18: =E18/(1+C18)^10 -> 0.15876639 | G18: =D18+F18 -> 0.55074292
B19: High | C19: =Assumptions!C24 -> 0.15 | D19: =NPV(C19,C8:L8) -> 0.36609859 | E19: =L8*(1+Assumptions!$C$18)/(C19-Assumptions!$C$18) -> 0.486306 | F19: =E19/(1+C19)^10 -> 0.12020741 | G19: =D19+F19 -> 0.486306
A21: MODERATE CASE
B22: Discount Rate | C22: Rate | D22: PV of Yrs 1-10 FCF | E22: Terminal Value (Yr 10) | F22: PV of Terminal Value | G22: Total NPV / Share
B23: Low | C23: =Assumptions!C22 -> 0.1 | D23: =NPV(C23,C13:L13) -> 0.729459 | E23: =L13*(1+Assumptions!$C$18)/(C23-Assumptions!$C$18) -> 1.8920288 | F23: =E23/(1+C23)^10 -> 0.729459 | G23: =D23+F23 -> 1.458918
B24: Base | C24: =Assumptions!C23 -> 0.13245 | D24: =NPV(C24,C13:L13) -> 0.62383412 | E24: =L13*(1+Assumptions!$C$18)/(C24-Assumptions!$C$18) -> 1.4284853 | F24: =E24/(1+C24)^10 -> 0.41179912 | G24: =D24+F24 -> 1.0356332
B25: High | C25: =Assumptions!C24 -> 0.15 | D25: =NPV(C25,C13:L13) -> 0.57591253 | E25: =L13*(1+Assumptions!$C$18)/(C25-Assumptions!$C$18) -> 1.2613525 | F25: =E25/(1+C25)^10 -> 0.31178705 | G25: =D25+F25 -> 0.88769958
A27: SUMMARY
C28: Conservative Case | D28: Moderate Case
B29: Low discount rate | C29: =G17 -> 0.729459 | D29: =G23 -> 1.458918
B30: Base discount rate | C30: =G18 -> 0.55074292 | D30: =G24 -> 1.0356332
B31: High discount rate | C31: =G19 -> 0.486306 | D31: =G25 -> 0.88769958
B32: Range across all scenarios | C32: =MIN(C29:D31) -> 0.486306 | D32: =MAX(C29:D31) -> 1.458918

Sheet Liquidation
A1: Liquidation Value
B3: Company: | C3: =Assumptions!C4 -> Chegg, Inc.
A5: NET-NET WORKING CAPITAL
C6: $mm
B7: Cash & equivalents | C7: =Assumptions!C27 -> 44.623
B8: Marketable securities | C8: =Assumptions!C28 -> 27.691
B9: Accounts receivable | C9: =Assumptions!C29 -> 10.734
B10: Inventory | C10: =Assumptions!C30 -> 0
B11: Other current assets | C11: =Assumptions!C31 -> 25.653
B12: Total current assets (undiscounted) | C12: =SUM(C7:C11) -> 108.701
B13: Less: total current liabilities | C13: =-Assumptions!C33 -> -92.96
B14: Less: long-term debt | C14: =-Assumptions!C34 -> 0
B15: Less: other long-term liabilities | C15: =-Assumptions!C35 -> -16.051
B16: Less: contingent/off-balance-sheet liabilities | C16: =-Assumptions!C36 -> 0
B17: Net-net working capital ($mm) | C17: =C12+SUM(C13:C16) -> -0.31
B18: Net-net working capital per share | C18: =C17/Assumptions!C7 -> -0.0025545898
B19: Net working capital (current assets less current liabilities) minus all long-term liabilities, a genuine worst-case floor
A21: ORDERLY vs. FIRE-SALE LIQUIDATION VALUE (pp. 143-144)
C22: Orderly | D22: Fire Sale
B23: Cash & equivalents (100% both cases) | C23: =Assumptions!C27 -> 44.623 | D23: =Assumptions!C27 -> 44.623
B24: Marketable securities, net of transaction cost | C24: =Assumptions!C28*(1-Assumptions!C39) -> 27.13718 | D24: =Assumptions!C28*(1-Assumptions!C39) -> 27.13718
B25: Accounts receivable, at recovery % | C25: =Assumptions!C29*Assumptions!C40 -> 9.6606 | D25: =Assumptions!C29*Assumptions!C41 -> 7.5138
B26: Inventory, at recovery % | C26: =Assumptions!C30*Assumptions!C42 -> 0 | D26: =Assumptions!C30*Assumptions!C43 -> 0
B27: Other current assets (assume orderly recovery %, both cases) | C27: =Assumptions!C31*Assumptions!C40 -> 23.0877 | D27: =Assumptions!C31*Assumptions!C41 -> 17.9571
B28: PP&E, at estimated liquidation value (your judgment) | C28: =Assumptions!C44 -> 0.94948 | D28: =Assumptions!C44*0.7 -> 0.664636
B29: Gross liquidation proceeds | C29: =SUM(C23:C28) -> 105.45796 | D29: =SUM(D23:D28) -> 97.895716
B30: Less: total liabilities (current + LT + contingent) | C30: =-(Assumptions!C33+Assumptions!C34+Assumptions!C35+Assumptions!C36) -> -109.011 | D30: =-(Assumptions!C33+Assumptions!C34+Assumptions!C35+Assumptions!C36) -> -109.011
B31: Net liquidation value ($mm) | C31: =C29+C30 -> -3.55304 | D31: =D29+D30 -> -11.115284
B32: Net liquidation value per share | C32: =C31/Assumptions!C7 -> -0.029279225 | D32: =D31/Assumptions!C7 -> -0.091596746

Sheet Market Multiples
A1: Private-Market Value & Stock Market Value
B3: Company: | C3: =Assumptions!C4 -> Chegg, Inc.
B4: Subject pretax cash flow ($mm): | C4: =Assumptions!C47 -> 49.2
A6: PRIVATE-MARKET VALUE
B7: Average multiple | C7: =AVERAGEIF(Assumptions!$D$50:$D$54,"Transaction",Assumptions!$C$50:$C$54) -> 14.6
B8: Number of comps in that average | C8: =COUNTIF(Assumptions!$D$50:$D$54,"Transaction") -> 1
B9: Implied enterprise value ($mm) | C9: =C4*C7 -> 718.32
B10: Less: total debt | C10: =-(Assumptions!C34) -> 0
B11: Plus: cash & equivalents | C11: =Assumptions!C27 -> 44.623
B12: Implied equity value ($mm) | C12: =C9-Assumptions!C34+Assumptions!C27 -> 762.943
B13: Implied value per share | C13: =C12/Assumptions!C7 -> 6.2871175
B14: Multiples paid by sophisticated private buyers for comparable whole businesses. These multiples drift with credit availability and buyer discipline.
A16: STOCK MARKET VALUE
B17: Average multiple | C17: =AVERAGEIF(Assumptions!$D$50:$D$54,"Trading",Assumptions!$C$50:$C$54) -> 8.15
B18: Number of comps in that average | C18: =COUNTIF(Assumptions!$D$50:$D$54,"Trading") -> 2
B19: Implied enterprise value ($mm) | C19: =C4*C17 -> 400.98
B20: Less: total debt | C20: =-(Assumptions!C34) -> 0
B21: Plus: cash & equivalents | C21: =Assumptions!C27 -> 44.623
B22: Implied equity value ($mm) | C22: =C19-Assumptions!C34+Assumptions!C27 -> 445.603
B23: Implied value per share | C23: =C22/Assumptions!C7 -> 3.6720416
B24: What comparable public companies trade for. Book calls this the least reliable of the three core methods, most useful for closed-end funds, holding companies, or spin-offs.

Sheet Summary
A1: Summary — Range of Value & Margin of Safety
B3: Company: | C3: =Assumptions!C4 -> Chegg, Inc.
B4: Current share price: | C4: =Assumptions!C6 -> 0.72
A6: VALUE ESTIMATES PER SHARE
C7: Value / Share | D7: Source / Note
B8: NPV / DCF — Conservative case, low end | C8: ='DCF NPV'!C32 -> 0.486306 | D8: Lowest of 6 DCF scenarios on DCF_NPV.
B9: NPV / DCF — Moderate case, high end | C9: ='DCF NPV'!D32 -> 1.458918 | D9: Highest of 6 DCF scenarios on DCF_NPV.
B10: Net-net working capital (Graham floor) | C10: =Liquidation!C18 -> -0.0025545898 | D10: Undiscounted current assets less every liability (pp. 144-145).
B11: Liquidation value — orderly wind-down | C11: =Liquidation!C32 -> -0.029279225 | D11: From the Liquidation tab.
B12: Liquidation value — fire sale | C12: =Liquidation!D32 -> -0.091596746 | D12: From the Liquidation tab.
B13: Private-market value | C13: ='Market Multiples'!C13 -> 6.2871175 | D13: Transaction-multiple comps (pp. 140-142).
B14: Stock market value | C14: ='Market Multiples'!C23 -> 3.6720416 | D14: Trading-multiple comps (pp. 145-147).
A16: RANGE & MARGIN OF SAFETY
B17: Lowest value estimate (most conservative) | C17: =MIN(C8:C14) -> -0.091596746
B18: Highest value estimate | C18: =MAX(C8:C14) -> 6.2871175
B19: Current share price | C19: =C4 -> 0.72
B20: Discount of price to lowest value estimate | C20: =IF(C17<=0,"n/a - lowest estimate is zero or negative",1-C4/C17) -> n/a - lowest estimate is zero or negative
B21: Your required margin of safety | C21: =Assumptions!C63 -> 0.33
B22: Price at which required margin of safety is met | C22: =C17*(1-C21) -> -0.06136982
B23: Meets your required margin of safety? | C23: =IF(ISNUMBER(C20),IF(C20>=C21,"Yes - price is at/below your target","No - price is above your target"),"n/a - see note above") -> n/a - see note above
B25: Reminder: the book does not prescribe a single required discount — margin of safety is defined as buying cheap enough to absorb your own forecasting error, bad luck, or market decline (Glossary, p. 244). Set the required-margin cell on the Assumptions tab to whatever discount you actually need to sleep at night, and revisit it if your conviction in the inputs above changes.
B27: Also revisit the range itself, not just the price: if the seven estimates above disagree sharply, that is itself information (p. 147) — it usually means one or more of your inputs (growth, discount rate, recovery %) deserves more scrutiny before you rely on the average.

Sheet Qtr Source Data
A1: Quarterly Source Data (as reported in Chegg SEC filings)
B2: $ in thousands, except per share.
A4: INCOME STATEMENT, AS REPORTED
B5: Period | C5: 3M Sep-23 | D5: 9M Sep-23 | E5: FY 2023 | F5: 3M Mar-24 | G5: 3M Jun-24 | H5: 3M Sep-24 | I5: 9M Sep-24 | J5: FY 2024 | K5: 3M Mar-25 | L5: 3M Jun-25 | M5: 3M Sep-25 | N5: 9M Sep-25 | O5: FY 2025 | P5: 3M Mar-26 | Q5: 3M Jun-26
B6: Net revenues | C6: 157854 | D6: 528308 | E6: 716295 | F6: 174350 | G6: 163147 | H6: 136593 | I6: 474090 | J6: 617574 | K6: 121387 | L6: 105120 | M6: 77742 | N6: 304249 | O6: 376908 | P6: 63262 | Q6: 51849
B7: Cost of revenues (positive = expense) | C7: 83575 | D7: 180137 | E7: 225941 | F7: 46497 | G7: 45411 | H7: 43420 | I7: 135328 | J7: 180927 | K7: 53973 | L7: 35478 | M7: 31701 | N7: 121152 | O7: 152151 | P7: 25374 | Q7: 23567
B8: Research and development | C8: 46202 | D8: 145981 | E8: 191705 | F8: 44435 | G8: 43651 | H8: 41337 | I8: 129423 | J8: 170431 | K8: 29428 | L8: 28717 | M8: 18350 | N8: 76495 | O8: 93453 | P8: 9139 | Q8: 7398
B9: Sales and marketing | C9: 28872 | D9: 96845 | E9: 126591 | F9: 30375 | G9: 23545 | H9: 26508 | I9: 80428 | J9: 108329 | K9: 25614 | L9: 17417 | M9: 11583 | N9: 54614 | O9: 68754 | P9: 10606 | Q9: 9468
B10: General and administrative | C10: 53475 | D10: 182757 | E10: 236183 | F10: 55534 | G10: 54016 | H10: 51910 | I10: 161460 | J10: 217756 | K10: 39374 | L10: 59966 | M10: 33232 | N10: 132572 | O10: 177406 | P10: 19180 | Q10: 14591
B11: Impairment expense | C11: 3600 | D11: 3600 | E11: 3600 | F11: 0 | G11: 481531 | H11: 195708 | I11: 677239 | J11: 677239 | K11: 2000 | L11: 0 | M11: 0 | N11: 2000 | O11: 2000 | P11: 0 | Q11: 0
B12: Interest expense, net | C12: -733 | D12: -3115 | E12: -3773 | F12: -650 | G12: -651 | H12: -658 | I12: -1959 | J12: -2590 | K12: -467 | L12: -41 | M12: -41 | N12: -549 | O12: -590 | P12: -31 | Q12: -22
B13: Other income, net | C13: 40492 | D13: 116671 | E13: 121810 | F13: 10780 | G13: 7119 | H13: 7586 | I13: 25485 | J13: 51332 | K13: 12997 | L13: 2059 | M13: 1377 | N13: 16433 | O13: 17304 | P13: 1156 | Q13: 638
B14: (Provision for) benefit from income taxes | C14: -172 | D14: -24029 | E14: -32132 | F14: -9059 | G14: -138345 | H14: 2723 | I14: -144681 | J14: -148702 | K14: -1012 | L14: -1223 | M14: -1683 | N14: -3918 | O14: -3279 | P14: 140 | Q14: -392
B15: Net income (loss), as reported | C15: -18283 | D15: 8515 | E15: 18180 | F15: -1420 | G15: -616884 | H15: -212639 | I15: -830943 | J15: -837068 | K15: -17484 | L15: -35663 | M15: -17471 | N15: -70618 | O15: -103421 | P15: 228 | Q15: -2951
B16: EPS, basic ($) | C16: -0.16 | F16: -0.01 | G16: -6.01 | H16: -2.05 | K16: -0.17 | L16: -0.33 | M16: -0.16 | P16: 0 | Q16: -0.03
B17: EPS, diluted ($) | C17: -0.16 | F17: -0.01 | G17: -6.01 | H17: -2.05 | K17: -0.17 | L17: -0.33 | M17: -0.16 | P17: 0 | Q17: -0.03
B18: Weighted avg shares, basic (000s) | C18: 115407 | F18: 102343 | G18: 102604 | H18: 103723 | K18: 105159 | L18: 106908 | M18: 108450 | P18: 111726 | Q18: 111422
B19: Weighted avg shares, diluted (000s) | C19: 115407 | F19: 102343 | G19: 102604 | H19: 103723 | K19: 105159 | L19: 106908 | M19: 108450 | P19: 112130 | Q19: 111422
A22: BALANCE SHEET, AS REPORTED
B23: Period end | C23: Sep 30, 2023 | D23: Dec 31, 2023 | E23: Mar 31, 2024 | F23: Jun 30, 2024 | G23: Sep 30, 2024 | H23: Dec 31, 2024 | I23: Mar 31, 2025 | J23: Jun 30, 2025 | K23: Sep 30, 2025 | L23: Dec 31, 2025 | M23: Mar 31, 2026 | N23: Jun 30, 2026
B24: Cash and cash equivalents | C24: 94419 | D24: 135757 | E24: 143747 | F24: 133068 | G24: 152073 | H24: 161475 | I24: 44105 | J24: 36825 | K24: 38180 | L24: 31146 | M24: 33526 | N24: 44623
B25: Short-term investments | C25: 166841 | D25: 194257 | E25: 247013 | F25: 212396 | G25: 209003 | H25: 154249 | I25: 44188 | J25: 48815 | K25: 58209 | L25: 41674 | M25: 32388 | N25: 27691
B26: Accounts receivable, net | C26: 30480 | D26: 31404 | E26: 24741 | F26: 20964 | G26: 23749 | H26: 23641 | I26: 28549 | J26: 18055 | K26: 15440 | L26: 15604 | M26: 17795 | N26: 10734
B27: Prepaid expenses | C27: 30761 | D27: 20980 | E27: 20429 | F27: 30841 | G27: 24706 | H27: 17100 | I27: 14514 | J27: 23683 | K27: 18742 | L27: 16331 | M27: 12128 | N27: 11352
B28: Other current assets | C28: 25195 | D28: 32437 | E28: 30010 | F28: 36279 | G28: 86980 | H28: 81094 | I28: 78395 | J28: 76548 | K28: 72788 | L28: 16857 | M28: 14948 | N28: 14301
B29: Long-term investments | C29: 412541 | D29: 249547 | E29: 221665 | F29: 259925 | G29: 270161 | H29: 212650 | I29: 38093 | J29: 28474 | K29: 15277 | L29: 12392 | M29: 1984 | N29: 0
B30: Property and equipment, net | C30: 168735 | D30: 183073 | E30: 188430 | F30: 179278 | G30: 177882 | H30: 170648 | I30: 144971 | J30: 135491 | K30: 125598 | L30: 115168 | M30: 105127 | N30: 94948
B31: Goodwill | C31: 617690 | D31: 631995 | E31: 628784 | F31: 189769 | G31: 0 | H31: 0 | I31: 0 | J31: 0 | K31: 0 | L31: 0 | M31: 0 | N31: 0
B32: Intangible assets, net | C32: 56638 | D32: 52430 | E32: 48143 | F32: 12848 | G32: 11424 | H32: 10347 | I32: 9271 | J32: 8194 | K32: 7117 | L32: 6041 | M32: 4964 | N32: 3957
B33: Right of use assets | C33: 26568 | D33: 25130 | E33: 23521 | F33: 21508 | G33: 29071 | H33: 22256 | I33: 21479 | J33: 19418 | K33: 18088 | L33: 13188 | M33: 12113 | N33: 11505
B34: Deferred tax assets | C34: 145807 | D34: 141843 | E34: 140200 | F34: 2287 | G34: 2308 | H34: 0 | I34: 0 | J34: 0 | K34: 0 | L34: 0 | M34: 0 | N34: 0
B35: Other assets | C35: 28964 | D35: 28382 | E35: 15961 | F35: 15167 | G35: 15315 | H35: 15491 | I35: 15204 | J35: 8950 | K35: 8832 | L35: 9613 | M35: 9129 | N35: 8514
... B49: Total stockholders' equity, as reported | C49: 1033349 | D49: 944618 | E49: 963474 | F49: 365500 | G49: 184981 | H49: 192981 | I49: 185671 | J49: 157856 | K49: 146053 | L49: 119623 | M49: 121143 | N49: 118614
A52: CASH FLOW STATEMENT, AS REPORTED YEAR-TO-DATE
B53: Period (year-to-date) | C53: 6M Jun-23 | D53: 9M Sep-23 | E53: FY 2023 | F53: 3M Mar-24 | G53: 6M Jun-24 | H53: 9M Sep-24 | I53: FY 2024 | J53: 3M Mar-25 | K53: 6M Jun-25 | L53: 9M Sep-25 | M53: FY 2025 | N53: 3M Mar-26 | O53: 6M Jun-26
B54: Net income (loss) | C54: 26798 | D54: 8515 | E54: 18180 | F54: -1420 | G54: -618304 | H54: -830943 | I54: -837068 | J54: -17484 | K54: -53147 | L54: -70618 | M54: -103421 | N54: 228 | O54: -2723
B55: Share-based compensation expense | C55: 69666 | D55: 101596 | E55: 133502 | F55: 29289 | G55: 47336 | H55: 69267 | I55: 84614 | J55: 11257 | K55: 19169 | L55: 25094 | M55: 31864 | N55: 2711 | O55: 5035
B56: Depreciation and amortization expense | C56: 52027 | D56: 108945 | E56: 129718 | F56: 19687 | G56: 39393 | H56: 58966 | I56: 78344 | J56: 32094 | K56: 48320 | L56: 63641 | M56: 78637 | N56: 13947 | O56: 26992
B57: Deferred income taxes | C57: 20142 | D57: 20929 | E57: 26575 | F57: 2877 | G57: 141032 | H57: 141103 | I57: 143319 | J57: 15 | K57: 149 | L57: 319 | M57: 1348 | N57: -95 | O57: -11
B58: Operating lease expense, net of accretion | C58: 3009 | D58: 4535 | E58: 6079 | F58: 1567 | G58: 3141 | H58: 4647 | I58: 5864 | J58: 1089 | K58: 2019 | L58: 2883 | M58: 3641 | N58: 545 | O58: 1076
B59: Amortization of debt issuance costs | C59: 1988 | D59: 2610 | E59: 3156 | F59: 541 | G59: 1081 | H59: 1628 | I59: 2147 | J59: 377 | K59: 418 | L59: 459 | M59: 500 | N59: 31 | O59: 53
B60: Loss from write-offs of property and equipment | C60: 450 | D60: 3578 | E60: 4137 | F60: 478 | G60: 1657 | H60: 2024 | I60: 5795 | J60: 2287 | K60: 558 | L60: 793 | M60: 1959 | N60: 49 | O60: 48
B61: Gain on early extinguishment of debt | C61: -53777 | D61: -85926 | E61: -85926 | F61: 0 | G61: 0 | H61: 0 | I61: -19515 | J61: -7360 | K61: -7360 | L61: -7360 | M61: -7838 | N61: -523 | O61: -523
B62: Realized (gain) loss on sale of investments | E62: 2106 | F62: 0 | G62: 0 | H62: 0 | I62: 27 | J62: -752 | K62: -752 | L62: -752 | M62: -752 | N62: -5 | O62: -5
B63: Impairment expense | C63: 0 | D63: 3600 | E63: 3600 | G63: 481531 | H63: 677239 | I63: 677239 | K63: 2000 | L63: 2000 | M63: 2000 | O63: 0
B64: Impairment of lease related assets | C64: 0 | D64: 0 | E64: 0 | G64: 2189 | H64: 2189 | I64: 5557 | K64: 3004 | L64: 3004 | M64: 7315 | O64: 0
B65: Impairment of strategic equity investment | E65: 0 | G65: 0 | H65: 0 | I65: 0 | K65: 6000 | L65: 6000 | M65: 6000 | O65: 0
B66: Loss contingency / litigation settlement | C66: 7000 | D66: 7000 | E66: 7000 | G66: 0 | H66: 5100 | I66: 0 | K66: 7500 | L66: 0 | M66: 0 | O66: -3000
B67: Other non-cash items | C67: -1083 | D67: -389 | E67: -1228 | F67: -31 | G67: 82 | H67: 222 | I67: 656 | J67: -28 | K67: 325 | L67: 1049 | M67: 1423 | N67: -159 | O67: -298
B68: Change in accounts receivable | C68: 3081 | D68: -6908 | E68: -7799 | F68: 6705 | G68: 10561 | H68: 8019 | I68: 7771 | J68: -4693 | K68: 6114 | L68: 8592 | M68: 8439 | N68: -2338 | O68: 4816
B69: Change in prepaid expenses and other current assets | C69: 15082 | D69: 558 | E69: 3476 | F69: 3583 | G69: -12173 | H69: -55725 | I69: -41732 | J69: 5880 | K69: -941 | L69: 7822 | M69: 66370 | N69: 6018 | O69: 7572
B70: Change in other assets | C70: 5470 | D70: 8671 | E70: 10829 | F70: -1270 | G70: -773 | H70: -469 | I70: 1130 | J70: 518 | K70: 928 | L70: 1323 | M70: 21 | N70: -268 | O70: 260
B71: Change in accounts payable | C71: -671 | D71: 4820 | E71: 13057 | F71: -6589 | G71: -12045 | H71: -8308 | I71: -12376 | J71: 1535 | K71: -6038 | L71: -4977 | M71: -9660 | N71: 3599 | O71: 1376
B72: Change in deferred revenue | C72: -3634 | D72: 2539 | E72: -1585 | F72: -1159 | G72: -10226 | H72: -11763 | I72: -15885 | J72: 5437 | K72: -5945 | L72: -8195 | M72: -10677 | N72: -608 | O72: -2839
B73: Change in accrued liabilities | C73: -1436 | D73: -6149 | E73: -7342 | F73: 640 | G73: -4057 | H73: 46849 | I73: 47103 | J73: -4894 | K73: -1113 | L73: -3301 | M73: -59723 | N73: -18186 | O73: -22846
B74: Change in other liabilities | C74: -8205 | D74: -9810 | E74: -11337 | F74: -1580 | G74: -2880 | H74: -2968 | I74: -7785 | J74: -752 | K74: -1522 | L74: -3277 | M74: -1956 | N74: -841 | O74: -822
B75: Purchases of property and equipment | C75: -33864 | D75: -57298 | E75: -83052 | F75: -28017 | G75: -45817 | H75: -61659 | I75: -74953 | J75: -8665 | K75: -15895 | L75: -21651 | M75: -28123 | N75: -1042 | O75: -4700
B76: Proceeds from disposition of textbooks | C76: 9787 | D76: 9787 | E76: 9787 | I76: 0 | M76: 0
B77: Purchases of investments | C77: -552409 | D77: -585275 | E77: -637939 | F77: -79028 | G77: -123669 | H77: -134213 | I77: -170950 | J77: -793 | K77: -793 | L77: -793 | M77: -793 | N77: 0 | O77: 0
B78: Maturities of investments | C78: 476862 | D78: 561197 | E78: 597197 | F78: 50731 | G78: 89890 | H78: 96907 | I78: 171671 | J78: 103214 | K78: 107710 | L78: 111124 | M78: 130055 | N78: 13477 | O78: 20031
B79: Proceeds from sale of investments | C79: 238681 | D79: 238681 | E79: 394533 | F79: 0 | G79: 0 | H79: 0 | I79: 70077 | J79: 181158 | K79: 181158 | L79: 181158 | M79: 181158 | N79: 5679 | O79: 5679
B80: Proceeds from sale of strategic equity investment | C80: 0 | D80: 0 | E80: 0 | F80: 15500 | G80: 15500 | H80: 15500 | I80: 15500 | J80: 0 | K80: 0 | L80: 0 | M80: 0
B81: Purchase of strategic equity investment | C81: -9604 | D81: -11853 | E81: -11853 | I81: 0 | M81: 0
B82: Proceeds from common stock issued under stock plans | C82: 3081 | D82: 3108 | E82: 4165 | G82: 2190 | H82: 2191 | I82: 2636 | K82: 391 | L82: 392 | M82: 590 | O82: 68
B83: Taxes paid on net share settlement of equity awards | C83: -11068 | D83: -13857 | E83: -16440 | F83: -4294 | G83: -7825 | H83: -8648 | I83: -9239 | J83: -469 | K83: -1037 | L83: -1642 | M83: -2600 | N83: -597 | O83: -774
B84: Payment of withholding tax | E84: 0 | I84: -3450 | M84: -1621
B85: Repurchase of common stock | C85: -186368 | D85: -186368 | E85: -334806 | I85: -2569 | M85: 0 | O85: -1721
B86: Repayment of convertible senior notes | C86: -369761 | D86: -505986 | E86: -505986 | G86: 0 | H86: 0 | I86: -96520 | J86: -416492 | K86: -416492 | L86: -416492 | M86: -424848 | N86: -19450 | O86: -19450
B87: Proceeds from capped call | C87: 297 | D87: 297 | E87: 297 | I87: 0 | M87: 0
B88: Effect of exchange rate changes | C88: 197 | D88: -379 | E88: 21 | F88: -226 | G88: -305 | H88: -149 | I88: -1025 | J88: 218 | K88: 491 | L88: -160 | M88: -256 | N88: -418 | O88: -451
B89: Net cash from operating activities, as reported | C89: 135907 | D89: 168714 | E89: 246198 | F89: 53318 | G89: 67545 | H89: 107077 | I89: 125205 | J89: 24526 | K89: 19686 | L89: 24499 | M89: 15490 | N89: 4105 | O89: 14161
B90: Net cash from investing activities, as reported | C90: 129453 | D90: 155239 | E90: 268673 | F90: -40814 | G90: -64096 | H90: -83465 | I90: 11345 | J90: 274914 | K90: 272180 | L90: 269838 | M90: 282297 | N90: 18114 | O90: 21010
B91: Net cash from financing activities, as reported | C91: -563819 | D91: -702806 | E91: -852770 | F91: -4294 | G91: -5635 | H91: -6457 | I91: -109142 | J91: -416961 | K91: -417138 | L91: -417742 | M91: -428479 | N91: -20047 | O91: -21877
