Workbook

Sheet Main
A2: LLY | D2: Name | E2: Indication | F2: Mechanism | G2: Economics | H2: Approved
A3: Price | B3: 1213.4 | D3: Mounjaro | E3: =Mounjaro!C4 -> Type 2 Diabetes | F3: =Mounjaro!C5 -> Dual GIP/GLP-1 Receptor Agonist | G3: 1 | H3: 44694
A4: Shares | B4: 895.9 | D4: Zepbound | E4: =Zepbound!C4 -> Obesity & Obstructive Sleep Apnea | F4: =Zepbound!C5 -> Dual GIP/GLP-1 Receptor Agonist | G4: 1 | H4: 45238
A5: Market Cap | B5: =B3*B4 -> 1087085.1 | D5: Trulicity | E5: =Trulicity!C4 -> Type-2 Diabetes | F5: =Trulicity!C5 -> GLP-1 Agonist | G5: 1 | H5: 41900
A6: Cash | B6: 7268 | D6: Retatrutide | E6: =Retatrutide!C4 -> Obesity & Type 2 Diabetes | F6: =Retatrutide!C5 -> GIP / GLP-1 / Glucagon Triple Receptor Agonist | G6: 1 | H6: TBD
A7: Debt | B7: =1635+40868 -> 42503 | D7: Foundayo | E7: =Foundayo!C4 -> Obesity / Chronic Weight Management | F7: =Foundayo!C5 -> GLP-1 Receptor Agonist (oral, nonpeptide) | G7: 1 | H7: 46113
A8: EV | B8: =B5+B7-B6 -> 1122320.1 | D8: Basaglar | E8: =Basaglar!C4 -> Type 1 and Type 2 Diabetes | F8: =Basaglar!C5 -> Long-Acting Insulin | G8: 1 | H8: =DATE(2015,12,16) -> 42354
D9: Humalog | E9: =Humalog!C4 -> Type 1 and Type 2 Diabetes | F9: =Humalog!C5 -> Rapid-Acting Insulin | G9: 1 | H9: 35230
D10: Humulin | E10: =Humulin!C4 -> Type 1 and Type 2 Diabetes | F10: =Humulin!C5 -> Insulin (short- and intermediate-acting) | G10: 1 | H10: =DATE(1982,10,28) -> 30252
D11: Jardiance | E11: =Jardiance!C4 -> Type 2 Diabetes & Heart Failure | F11: =Jardiance!C5 -> SGLT2 Inhibitors | G11: Royalty only | H11: 41852
D12: Verzenio | E12: =Verzenio!C4 -> Breast Cancer | F12: =Verzenio!C5 -> CDK4/6 inhibitors | G12: 1 | H12: 43006
D13: Cyramza | E13: =Cyramza!C4 -> Gastric, NSCLC, and Colorectal Cancer | F13: =Cyramza!C5 -> VEGFR2 Antagonist (Monoclonal Antibody) | G13: 1 | H13: =DATE(2014,4,21) -> 41750
D14: Erbitux | E14: =Erbitux!C4 -> Colorectal and Head & Neck Cancer | F14: =Erbitux!C5 -> EGFR Inhibitor (Monoclonal Antibody) | G14: Royalty / share | H14: =DATE(2004,2,12) -> 38029
D15: Retevmo | E15: =Retevmo!C4 -> RET-Altered NSCLC and Thyroid Cancer | F15: =Retevmo!C5 -> RET Kinase Inhibitor | G15: 1 | H15: =DATE(2020,5,8) -> 43959
D16: Tyvyt | E16: =Tyvyt!C4 -> Hodgkin Lymphoma, NSCLC & other cancers (approved in China; not FDA-approved) | F16: =Tyvyt!C5 -> PD-1 Inhibitor (Monoclonal Antibody) | G16: Royalty / share | H16: Not FDA approved
D17: Jaypirca | E17: =Jaypirca!C4 -> Non-Hodgkin Lymphoma | F17: =Jaypirca!C5 -> Bruton’s tyrosine kinase (BTK) inhibitor | G17: 1 | H17: 44953
D18: Inluriyo | E18: =Inluriyo!C4 -> Breast Cancer | F18: =Inluriyo!C5 -> Estrogen Antagonist | G18: 1 | H18: 45925
D19: Ebglyss | E19: =Ebglyss!C4 -> Eczema | F19: =Ebglyss!C5 -> interleukin-13 antagonist | G19: 1 | H19: 45548
D20: Olumiant | E20: =Olumiant!C4 -> Rheumatoid Arthritis, Alopecia Areata, COVID-19 | F20: =Olumiant!C5 -> JAK (Janus Kinase) Inhibitor | G20: 1 | H20: =DATE(2018,5,31) -> 43251
D21: Omvoh | E21: =Omvoh!C4 -> Crohn's Disease & Ulcerative Colitis | F21: =Omvoh!C5 -> interleukin-23 antagonist | G21: 1 | H21: 45225
D22: Taltz | E22: =Taltz!C4 -> Plaque Psoriasis & Psoriatic Arthritis | F22: =Taltz!C5 -> interleukin antagonist | G22: 1 | H22: 42451
D23: Emgality | E23: =Emgality!C4 -> Migraine Prevention and Cluster Headache | F23: =Emgality!C5 -> CGRP Antagonist (Monoclonal Antibody) | G23: 1 | H23: =DATE(2018,9,27) -> 43370
D24: Kisunla | E24: =Kisunla!C4 -> Alzheimer's Disease | F24: =Kisunla!C5 -> amyloid beta-directed antibody | G24: 1 | H24: 45475

Sheet Model
B2: Eli Lilly and Company (LLY)
B4: Historic Quarterly IS | C4: Q1'23 | D4: Q2'23 | E4: Q3'23 | F4: Q4'23 | G4: Q1'24 | H4: Q2'24 | I4: Q3'24 | J4: Q4'24 | K4: Q1'25 | L4: Q2'25 | M4: Q3'25 | N4: Q4'25 | O4: Q1'26 | P4: Q2'26
B5: Diabetes | C5: =SUM(C6:C14) -> 4045.3 | D5: =SUM(D6:D14) -> 4260.4 | E5: =SUM(E6:E14) -> 4565.4 | F5: =SUM(F6:F14) -> 5588.7 | G5: =SUM(G6:G14) -> 5369.2 | H5: =SUM(H6:H14) -> 7858.8 | I5: =SUM(I6:I14) -> 7261.6 | J5: =SUM(J6:J14) -> 8962.7 | ... P5: =SUM(P6:P14) -> 14969
B6: Mounjaro | C6: 568.5 | D6: 979.7 | E6: 1409.3 | F6: 2205.6 | G6: 1806.5 | H6: 3090.8 | I6: 3112.7 | J6: 3530 | K6: 3842 | L6: 5198.9 | M6: 6515.1 | N6: 7409 | O6: 8662 | P6: 9943
B7: Zepbound | F7: 175.8 | G7: 517.4 | H7: 1243.2 | I7: 1257.8 | J7: 1907 | K7: 2312 | L7: 3381.4 | M7: 3588 | N7: 4261 | O7: 4160 | P7: 4928
B8: Trulicity | C8: 1977.1 | D8: 1812.5 | E8: 1673.6 | F8: 1669.3 | G8: 1456.3 | H8: 1245.6 | I8: 1301.4 | J8: 1250.2 | K8: 1095 | L8: 1092.2 | M8: 1051.8 | N8: =4276-M8-L8-K8 -> 1037 | O8: 919
B9: Retatrutide
B10: Foundayo | P10: 98
B11: Basaglar | C11: 209.3 | D11: 154.2 | E11: 179.6 | F11: =728.3-E11-D11-C11 -> 185.2 | G11: 157.6 | H11: 180.8 | I11: 161.6 | J11: 176.9 | K11: 173.6 | L11: 145 | M11: 162.2 | N11: =+J11 -> 176.9 | O11: =+K11-10 -> 163.6
B12: Humalog | C12: 460.9 | D12: 440.4 | E12: 395.4 | F12: 366.6 | G12: 538.7 | H12: 631.6 | I12: 534.6 | J12: 619.9 | K12: 537.2 | L12: 503.1 | M12: 599.1 | N12: =+M12-5 -> 594.1 | O12: =+N12--15 -> 609.1
B13: Humulin | C13: 252 | D13: 205.3 | E13: 206.7 | F13: =852.1-E13-D13-C13 -> 188.1 | G13: 206.2 | H13: 223.6 | I13: 207.1 | J13: 280.3 | K13: 173.2 | L13: 175.2 | M13: 176.6 | N13: =+J13 -> 280.3 | O13: =+K13-10 -> 163.2
B14: Jardiance | C14: 577.5 | D14: 668.3 | E14: 700.8 | F14: 798.1 | G14: 686.5 | H14: 1243.2 | I14: 686.4 | J14: 1198.4 | K14: 1014 | L14: 690 | M14: 959 | N14: =3431-K14-L14-M14 -> 768 | O14: 1114
B15: Oncology | C15: =SUM(C16:C22) -> 1230 | D15: =SUM(D16:D22) -> 1518.6 | E15: =SUM(E16:E22) -> 1596.7 | F15: =SUM(F16:F22) -> 1736.2 | G15: =SUM(G16:G22) -> 1660.7 | H15: =SUM(H16:H22) -> 2043.2 | I15: =SUM(I16:I22) -> 2102.6 | J15: =SUM(J16:J22) -> 2328.2 | ... P15: =SUM(P16:P22) -> 267
B16: Verzenio | C16: 750.9 | D16: 926.8 | E16: 1040.2 | F16: 1145.4 | G16: 1050.3 | H16: 1331.9 | I16: 1369.3 | J16: 1555 | K16: 1158.9 | L16: 1489.3 | M16: 1470.2 | N16: 1604 | O16: 1302
B17: Cyramza | C17: 236.8 | D17: 260.3 | E17: 224.1 | F17: 253.6 | G17: 229.9 | H17: 248.9 | I17: 236 | J17: 258.6 | K17: 224.9 | L17: 253.7 | M17: 245.5 | N17: =+J17 -> 258.6 | O17: =+K17+34 -> 258.9
B18: Erbitux | C18: 129.9 | D18: 162.5 | E18: 153.9 | F18: =596.5-E18-D18-C18 -> 150.2 | G18: 144.6 | H18: 155.8 | I18: 152 | J18: 175 | K18: 149 | L18: 183.7 | M18: 198.6 | N18: =+J18 -> 175 | O18: =+K18+34 -> 183
B19: Retevmo | C19: 51.4 | D19: 65.4 | E19: 63.4 | F19: 73.4 | G19: 69.2 | H19: 91.2 | I19: 114 | J19: 90 | K19: 91 | L19: 125.3 | M19: 112 | N19: =+M19+5 -> 117 | O19: =+N19+34 -> 151
B20: Tyvyt | C20: 61 | D20: 103.6 | E20: 115.1 | F20: 113.6 | G20: 116.7 | H20: 123 | I20: 150.2 | J20: 136 | K20: 137.5 | L20: 137.3 | M20: 141.8 | N20: =+J20 -> 136 | O20: =+K20+34+2 -> 173.5
B21: Jaypirca | G21: 50 | H21: 92.4 | I21: 81.1 | J21: 113.6 | K21: 92 | L21: 123.3 | M21: 142.9 | N21: =+M21+10 -> 152.9 | O21: 165 | P21: 192
B22: Inluriyo | L22: =M22-10 -> 5 | M22: =N22-10 -> 15 | N22: =O22-10 -> 25 | O22: 35 | P22: 75
B23: Immunology | C23: =SUM(C24:C27) -> 755.9 | D23: =SUM(D24:D27) -> 922.8 | E23: =SUM(E24:E27) -> 975.6 | F23: =SUM(F24:F27) -> 1028.1 | G23: =SUM(G24:G27) -> 834 | H23: =SUM(H24:H27) -> 1082.3 | I23: =SUM(I24:I27) -> 1185.8 | J23: =SUM(J24:J27) -> 1290.9 | ... P23: =SUM(P24:P27) -> 303
B24: Ebglyss | G24: 3.1 | H24: 4.3 | I24: 14.9 | J24: 20.4 | K24: 60.2 | L24: 86.8 | M24: 127.1 | N24: =+M24+5 -> 132.1 | O24: 145 | P24: 201
B25: Olumiant | C25: 228.9 | D25: 218.9 | E25: 231.4 | F25: 243.5 | G25: 217.4 | H25: 227.7 | I25: 250.8 | J25: 261.6 | K25: 228.7 | L25: 246.4 | M25: 268.9 | N25: =+J25 -> 261.6 | O25: =+K25+16 -> 244.7
B26: Omvoh | G26: 9.4 | H26: 25.6 | I26: 40.5 | J26: 56.9 | K26: 37.2 | L26: 74.8 | M26: 64.9 | N26: =+M26+25 -> 89.9 | O26: 80 | P26: 102
B27: Taltz | C27: 527 | D27: 703.9 | E27: 744.2 | F27: 784.6 | G27: 604.1 | H27: 824.7 | I27: 879.6 | J27: 952 | K27: 762 | L27: 847.6 | M27: 901.5 | N27: =3563-K27-L27-M27 -> 1051.9 | O27: 733
B28: Neuroscience | C28: =SUM(C29:C30) -> 154.3 | D28: =SUM(D29:D30) -> 169.3 | E28: =SUM(E29:E30) -> 168.5 | F28: =SUM(F29:F30) -> 186.1 | G28: =SUM(G29:G30) -> 225.7 | H28: =SUM(H29:H30) -> 192 | I28: =SUM(I29:I30) -> 204.3 | J28: =SUM(J29:J30) -> 257.7 | ... P28: =SUM(P29:P30) -> 167
B29: Emgality | C29: 154.3 | D29: 169.3 | E29: 168.5 | F29: 186.1 | G29: 225.7 | H29: 192 | I29: 202.9 | J29: 249.8 | K29: 124.6 | L29: 201.1 | M29: 175.7 | N29: =+J29*1.1 -> 274.78 | O29: =+K29*1.1 -> 137.06
B30: Kisunla | I30: 1.4 | J30: 7.9 | K30: 21.5 | L30: 48.6 | M30: 70.4 | N30: =+M30+25 -> 95.4 | O30: 124 | P30: 167
B31: Other / Misc | C31: =C32-(C5+C15+C23+C28) -> 774.5 | D31: =D32-(D5+D15+D23+D28) -> 1441 | E31: =E32-(E5+E15+E23+E28) -> 2192.4 | F31: =F32-(F5+F15+F23+F28) -> 814.3 | G31: =G32-(G5+G15+G23+G28) -> 678.4 | H31: =H32-(H5+H15+H23+H28) -> 126.5 | I31: =I32-(I5+I15+I23+I28) -> 684.8 | J31: =J32-(J5+J15+J23+J28) -> 693.3 | ... O31: =O32-(O5+O15+O23+O28) -> 275.94
B32: Total Revenue | C32: 6960 | D32: 8312.1 | E32: 9498.6 | F32: 9353.4 | G32: 8768 | H32: 11302.8 | I32: 11439.1 | J32: 13532.8 | K32: 12729 | L32: 15557.7 | M32: 17600.8 | N32: 19292 | O32: 19799 | P32: 22974
B33: COGS | C33: 1626.7 | D33: 1807.4 | E33: 1860.1 | F33: 1788 | G33: 1673.5 | H33: 2170.2 | I33: 2170.8 | J33: 2403.8 | K33: 2225 | L33: 2447.8 | M33: 3008.3 | N33: 3371.7 | O33: 3577 | P33: 3268
B34: Gross Margin | C34: =C32-C33 -> 5333.3 | D34: =D32-D33 -> 6504.7 | E34: =E32-E33 -> 7638.5 | F34: =F32-F33 -> 7565.4 | G34: =G32-G33 -> 7094.5 | H34: =H32-H33 -> 9132.6 | I34: =I32-I33 -> 9268.3 | J34: =J32-J33 -> 11129 | ... P34: =P32-P33 -> 19706
B35: R&D | C35: 1985.1 | D35: 2356.5 | E35: 2409.1 | F35: 2562.7 | G35: 2522.8 | H35: 2711.2 | I35: 2734.1 | J35: 3022.5 | K35: 2734 | L35: 3336.1 | M35: 3465.7 | N35: 3801.5 | O35: 3510 | P35: 3819
B36: SG&A | C36: 1749.2 | D36: 1925.4 | E36: 1803.9 | F36: 1924.6 | G36: 1952.2 | H36: 2117.3 | I36: 2099.8 | J36: 2424.5 | K36: 2468 | L36: 2753 | M36: 2740.7 | N36: 3131.4 | O36: 2934 | P36: 3430
B37: IPR&D | C37: 105 | D37: 97.1 | E37: 2975.1 | F37: 622.6 | G37: 110.5 | H37: 154.3 | I37: 2826.4 | J37: 189.2 | K37: 1572 | L37: 153 | M37: 655.7 | N37: 528.8 | O37: 584 | P37: 2776
B38: Asset Impairement/Resturcturing | C38: 0 | D38: 0 | E38: 0 | F38: 67.7 | G38: 0 | H38: 435 | I38: 81.6 | J38: 344 | K38: 35 | L38: 0 | M38: 364.9 | N38: 84.1 | O38: 279 | P38: 703
B39: Other expenses | C39: -35.7 | D39: 36.8 | E39: 23.2 | F39: 121 | G39: -27.1 | H39: 197.6 | I39: -62 | J39: 110.2 | K39: 239 | L39: 90.6 | M39: 133.1 | N39: 108.3 | O39: 65 | P39: -269
B40: Pre Tax Income | C40: =C34-(SUM(C35:C39)) -> 1529.7 | D40: =D34-(SUM(D35:D39)) -> 2088.9 | E40: =E34-(SUM(E35:E39)) -> 427.2 | F40: =F34-(SUM(F35:F39)) -> 2266.8 | G40: =G34-(SUM(G35:G39)) -> 2536.1 | H40: =H34-(SUM(H35:H39)) -> 3517.2 | I40: =I34-(SUM(I35:I39)) -> 1588.4 | J40: =J34-(SUM(J35:J39)) -> 5038.6 | ... P40: =P34-(SUM(P35:P39)) -> 9247
B41: Taxes | C41: 184.8 | D41: 325.7 | E41: 484.6 | F41: 319.1 | G41: 293.2 | H41: 550.2 | I41: 618.1 | J41: 628.9 | K41: 697 | L41: 1115.9 | M41: 1649.9 | N41: 1628.5 | O41: 1454 | P41: 2152
B42: Net Income | C42: =C40-C41 -> 1344.9 | D42: =D40-D41 -> 1763.2 | E42: =E40-E41 -> -57.4 | F42: =F40-F41 -> 1947.7 | G42: =G40-G41 -> 2242.9 | H42: =H40-H41 -> 2967 | I42: =I40-I41 -> 970.3 | J42: =J40-J41 -> 4409.7 | ... P42: =P40-P41 -> 7095
B43: EPS | C43: =C42/C44 -> 1.4888741 | D43: =D42/D44 -> 1.9526024 | E43: =E42/E44 -> -0.063791954 | F43: =F42/F44 -> 2.1617092 | G43: =G42/G44 -> 2.4816331 | H43: =H42/H44 -> 3.2813537 | I43: =I42/I44 -> 1.0721547 | J43: =J42/J44 -> 4.8779867 | ... P43: =P42/P44 -> 7.9391633
B44: Shares | C44: 903.3 | D44: 903 | E44: 899.8 | F44: 901 | G44: 903.8 | H44: 904.2 | I44: 905 | J44: 904 | K44: 900.6 | L44: 899.8 | M44: 898.8 | N44: 898 | O44: 895.9 | P44: 893.671
B46: Historic Drivers
B47: Historic Diabetes Revenue Growth Rate | C47: 0 | D47: 0 | E47: 0 | F47: 0 | G47: =(G5-C5)/C5 -> 0.32726868 | H47: =(H5-D5)/D5 -> 0.84461553 | I47: =(I5-E5)/E5 -> 0.59057257 | J47: =(J5-F5)/F5 -> 0.60371822 | K47: =(K5-G5)/G5 -> 0.70360575 | L47: =(L5-H5)/H5 -> 0.42334708 | M47: =(M5-I5)/I5 -> 0.79737248 | N47: =(N5-J5)/J5 -> 0.62075044 | ... P47: =(P5-L5)/L5 -> 0.33821452
B48: Historic Oncology Revenue Growth Rate | C48: 0 | D48: 0 | E48: 0 | F48: 0 | G48: =(G15-C15)/C15 -> 0.3501626 | H48: =(H15-D15)/D15 -> 0.34544976 | I48: =(I15-E15)/E15 -> 0.31684098 | J48: =(J15-F15)/F15 -> 0.34097454 | K48: =(K15-G15)/G15 -> 0.11597519 | L48: =(L15-H15)/H15 -> 0.13429914 | M48: =(M15-I15)/I15 -> 0.10624941 | N48: =(N15-J15)/J15 -> 0.060261146 | ... P48: =(P15-L15)/L15 -> -0.88479462
B49: Historic Immunology Revenue Growth Rate | C49: 0 | D49: 0 | E49: 0 | F49: 0 | G49: =(G23-C23)/C23 -> 0.10332055 | H49: =(H23-D23)/D23 -> 0.17284352 | I49: =(I23-E23)/E23 -> 0.21545715 | J49: =(J23-F23)/F23 -> 0.25561716 | K49: =(K23-G23)/G23 -> 0.30467626 | L49: =(L23-H23)/H23 -> 0.16012196 | M49: =(M23-I23)/I23 -> 0.14892899 | N49: =(N23-J23)/J23 -> 0.18948021 | ... P49: =(P23-L23)/L23 -> -0.75868111
B50: Historic Neuroscience Revenue Growth Rate | C50: 0 | D50: 0 | E50: 0 | F50: 0 | G50: =(G28-C28)/C28 -> 0.46273493 | H50: =(H28-D28)/D28 -> 0.13408151 | I50: =(I28-E28)/E28 -> 0.21246291 | J50: =(J28-F28)/F28 -> 0.38473939 | K50: =(K28-G28)/G28 -> -0.35268055 | L50: =(L28-H28)/H28 -> 0.30052083 | M50: =(M28-I28)/I28 -> 0.20460108 | N50: =(N28-J28)/J28 -> 0.43647652 | ... P50: =(P28-L28)/L28 -> -0.33119744
B51: Historic Other Revenue Growth Rate | C51: 0 | D51: 0 | E51: 0 | F51: 0 | G51: =(G31-C31)/C31 -> -0.12408005 | H51: =(H31-D31)/D31 -> -0.91221374 | I51: =(I31-E31)/E31 -> -0.68764824 | J51: =(J31-F31)/F31 -> -0.14859388 | K51: =(K31-G31)/G31 -> -0.27107901 | L51: =(L31-H31)/H31 -> 3.3399209 | M51: =(M31-I31)/I31 -> -0.10265771 | N51: =(N31-J31)/J31 -> -0.43528054 | ... P51: =(P31-L31)/L31 -> -1
B52: Historic Gross Margin % | C52: =C34/C32 -> 0.76627874 | D52: =D34/D32 -> 0.78255796 | E52: =E34/E32 -> 0.80417114 | F52: =F34/F32 -> 0.80883957 | G52: =G34/G32 -> 0.80913549 | H52: =H34/H32 -> 0.80799448 | I52: =I34/I32 -> 0.81022983 | J52: =J34/J32 -> 0.82237231 | ... P52: =P34/P32 -> 0.85775224
B53: Historic R&D % | C53: =C35/C34 -> 0.37220858 | D53: =D35/D34 -> 0.36227651 | E53: =E35/E34 -> 0.31538915 | F53: =F35/F34 -> 0.33873952 | G53: =G35/G34 -> 0.35559941 | H53: =H35/H34 -> 0.29687055 | I53: =I35/I34 -> 0.29499477 | J53: =J35/J34 -> 0.27158774 | ... P53: =P35/P34 -> 0.19379884
B54: Historic SG&A % | C54: =C36/C34 -> 0.32797705 | D54: =D36/D34 -> 0.29600135 | E54: =E36/E34 -> 0.23615893 | F54: =F36/F34 -> 0.25439501 | G54: =G36/G34 -> 0.27517091 | H54: =H36/H34 -> 0.23183978 | I54: =I36/I34 -> 0.22655719 | J54: =J36/J34 -> 0.21785425 | ... P54: =P36/P34 -> 0.17405866
B55: Historic IPR&D & | C55: =C37/C34 -> 0.019687623 | D55: =D37/D34 -> 0.014927668 | E55: =E37/E34 -> 0.38948746 | F55: =F37/F34 -> 0.082295715 | G55: =G37/G34 -> 0.015575446 | H55: =H37/H34 -> 0.016895517 | I55: =I37/I34 -> 0.30495344 | J55: =J37/J34 -> 0.017000629 | ... P55: =P37/P34 -> 0.1408708
B56: Historic Tax rate | C56: =C41/C40 -> 0.120808 | D56: =D41/D40 -> 0.15591938 | E56: =E41/E40 -> 1.1343633 | F56: =F41/F40 -> 0.14077113 | G56: =G41/G40 -> 0.11561058 | H56: =H41/H40 -> 0.15643125 | I56: =I41/I40 -> 0.38913372 | J56: =J41/J40 -> 0.12481642 | ... P56: =P41/P40 -> 0.23272413
B62: Assumptions | F62: =F79 -> FY'26 | G62: =G79 -> FY'27 | H62: =H79 -> FY'28 | I62: =I79 -> FY'29 | J62: =J79 -> FY'30 | K62: =K79 -> FY'31 | L62: =L79 -> FY'32 | M62: =M79 -> FY'33 | ... P62: =P79 -> FY'36
B63: Diabetes Revenue Growth Rate | F63: =AVERAGE(G47:O47) -> 0.6263998
B64: Oncology Revenue Growth Rate | F64: =AVERAGE(G48:O48) -> 0.22157685
B65: Immunology Revenue Growth Rate | F65: =AVERAGE(G49:O49) -> 0.18397411
B66: Neuroscience Revenue Growth Rate | F66: =AVERAGE(G50:O50) -> 0.28553277
B67: Other Revenue Growth Rate | F67: =AVERAGE(G51:O51) -> 0.024042886
B68: Gross Margin % | F68: =AVERAGE(C52:P52) -> 0.81506008
B69: R&D % | F69: =O53 -> 0.21637283
B70: SG&A % | F70: =O54 -> 0.18086549
B71: IPR&D & | F71: =O55 -> 0.036000493
B72: Tax rate | F72: 0.2
B79: Annual Income Statement | C79: FY'23 | D79: FY'24 | E79: FY'25 | F79: FY'26 | G79: FY'27 | H79: FY'28 | I79: FY'29 | J79: FY'30 | K79: FY'31 | L79: FY'32 | M79: FY'33 | N79: FY'34 | O79: FY'35 | P79: FY'36
B80: Diabetes | C80: =SUM(C5:F5) -> 18459.8 | D80: =SUM(G5:J5) -> 29452.3 | E80: =SUM(K5:N5) -> 47910.9 | F80: =SUM(F81:F89) -> 0 | G80: =SUM(G81:G89) -> 0 | H80: =SUM(H81:H89) -> 0 | I80: =SUM(I81:I89) -> 0 | J80: =SUM(J81:J89) -> 0 | K80: =SUM(K81:K89) -> 0 | L80: =SUM(L81:L89) -> 0 | M80: =SUM(M81:M89) -> 0 | ... P80: =SUM(P81:P89) -> 0
B81: Mounjaro | C81: =SUM(C6:F6) -> 5163.1 | D81: =SUM(G6:J6) -> 11540 | E81: =SUM(K6:N6) -> 22965
B82: Zepbound | C82: =SUM(C7:F7) -> 175.8 | D82: =SUM(G7:J7) -> 4925.4 | E82: =SUM(K7:N7) -> 13542.4
B83: Trulicity | C83: =SUM(C8:F8) -> 7132.5 | D83: =SUM(G8:J8) -> 5253.5 | E83: =SUM(K8:N8) -> 4276
B84: Retatrutide | C84: =SUM(C9:F9) -> 0 | D84: =SUM(G9:J9) -> 0 | E84: =SUM(K9:N9) -> 0
B85: Foundayo | C85: =SUM(C10:F10) -> 0 | D85: =SUM(G10:J10) -> 0 | E85: =SUM(K10:N10) -> 0
B86: Basaglar | C86: =SUM(C11:F11) -> 728.3 | D86: =SUM(G11:J11) -> 676.9 | E86: =SUM(K11:N11) -> 657.7
B87: Humalog | C87: =SUM(C12:F12) -> 1663.3 | D87: =SUM(G12:J12) -> 2324.8 | E87: =SUM(K12:N12) -> 2233.5
B88: Humulin | C88: =SUM(C13:F13) -> 852.1 | D88: =SUM(G13:J13) -> 917.2 | E88: =SUM(K13:N13) -> 805.3
B89: Jardiance | C89: =SUM(C14:F14) -> 2744.7 | D89: =SUM(G14:J14) -> 3814.5 | E89: =SUM(K14:N14) -> 3431
B90: Oncology | C90: =SUM(C15:F15) -> 6081.5 | D90: =SUM(G15:J15) -> 8134.7 | E90: =SUM(K15:N15) -> 8965.4 | F90: 9295.0862 | G90: 9523.8691 | H90: 9824.6269 | I90: 10212.308 | J90: 3660.6567 | K90: 3070.227 | L90: 3070.227 | M90: 3070.227 | N90: 3070.227 | O90: 3070.227 | P90: 3070.227
B91: Verzenio | C91: =SUM(C16:F16) -> 3863.3 | D91: =SUM(G16:J16) -> 5306.5 | E91: =SUM(K16:N16) -> 5722.4
B92: Cyramza | C92: =SUM(C17:F17) -> 974.8 | D92: =SUM(G17:J17) -> 973.4 | E92: =SUM(K17:N17) -> 982.7
B93: Erbitux | C93: =SUM(C18:F18) -> 596.5 | D93: =SUM(G18:J18) -> 627.4 | E93: =SUM(K18:N18) -> 706.3
B94: Retevmo | C94: =SUM(C19:F19) -> 253.6 | D94: =SUM(G19:J19) -> 364.4 | E94: =SUM(K19:N19) -> 445.3
B95: Tyvyt | C95: =SUM(C20:F20) -> 393.3 | D95: =SUM(G20:J20) -> 525.9 | E95: =SUM(K20:N20) -> 552.6
B96: Jaypirca | C96: =SUM(C21:F21) -> 0 | D96: =SUM(G21:J21) -> 337.1 | E96: =SUM(K21:N21) -> 511.1
B97: Inluriyo | C97: =SUM(C22:F22) -> 0 | D97: =SUM(G22:J22) -> 0 | E97: =SUM(K22:N22) -> 45
B98: Immunology | C98: =SUM(C23:F23) -> 3682.4 | D98: =SUM(G23:J23) -> 4393 | E98: =SUM(K23:N23) -> 5241.6 | F98: 6062.516 | G98: 6780.1266 | H98: 7365.8161 | I98: 8009.1513 | J98: 7491.2379 | K98: 7849.7016 | L98: 8150.0194 | M98: 8465.3532 | N98: 8796.4536 | O98: 9144.109 | P98: 9509.1473
B99: Ebglyss | C99: =SUM(C24:F24) -> 0 | D99: =SUM(G24:J24) -> 42.7 | E99: =SUM(K24:N24) -> 406.2
B100: Olumiant | C100: =SUM(C25:F25) -> 922.7 | D100: =SUM(G25:J25) -> 957.5 | E100: =SUM(K25:N25) -> 1005.6
B101: Omvoh | C101: =SUM(C26:F26) -> 0 | D101: =SUM(G26:J26) -> 132.4 | E101: =SUM(K26:N26) -> 266.8
B102: Taltz | C102: =SUM(C27:F27) -> 2759.7 | D102: =SUM(G27:J27) -> 3260.4 | E102: =SUM(K27:N27) -> 3563
B103: Neuroscience | C103: =SUM(C28:F28) -> 678.2 | D103: =SUM(G28:J28) -> 879.7 | E103: =SUM(K28:N28) -> 1012.08 | F103: 1043.4318 | G103: 1077.2202 | H103: 1113.6819 | I103: 1153.0772 | J103: 1195.6923 | K103: 1241.842 | L103: 1241.842 | M103: 1241.842 | N103: 1241.842 | O103: 1241.842 | P103: 1241.842
B104: Emgality | C104: =SUM(C29:F29) -> 678.2 | D104: =SUM(G29:J29) -> 870.4 | E104: =SUM(K29:N29) -> 776.18
B105: Kisunla | C105: =SUM(C30:F30) -> 0 | D105: =SUM(G30:J30) -> 9.3 | E105: =SUM(K30:N30) -> 235.9
B106: Other | C106: =SUM(C31:F31) -> 5222.2 | D106: =SUM(G31:J31) -> 2183 | E106: =SUM(K31:N31) -> 2049.52
B107: Total Revenue | C107: =C80+C90+C98+C103+C106 -> 34124.1 | D107: =D80+D90+D98+D103+D106 -> 45042.7 | E107: =E80+E90+E98+E103+E106 -> 65179.5 | F107: =F80+F90+F98+F103+F106 -> 16401.034 | G107: =G80+G90+G98+G103+G106 -> 17381.216 | H107: =H80+H90+H98+H103+H106 -> 18304.125 | I107: =I80+I90+I98+I103+I106 -> 19374.537 | J107: =J80+J90+J98+J103+J106 -> 12347.587 | ... P107: =P80+P90+P98+P103+P106 -> 13821.216
B108: COGS | C108: =SUM(C33:F33) -> 7082.2 | D108: =SUM(G33:J33) -> 8418.3 | E108: =SUM(K33:N33) -> 11052.8 | F108: =F107*(1-$F$68) -> 3033.2058 | G108: =G107*(1-$F$68) -> 3214.4806 | H108: =H107*(1-$F$68) -> 3385.1633 | I108: =I107*(1-$F$68) -> 3583.1252 | J108: =J107*(1-$F$68) -> 2283.5617 | K108: =K107*(1-$F$68) -> 2249.1968 | L108: =L107*(1-$F$68) -> 2304.7376 | M108: =M107*(1-$F$68) -> 2363.0554 | ... P108: =P107*(1-$F$68) -> 2556.0946
B109: Gross Margin | C109: =SUM(C34:F34) -> 27041.9 | D109: =SUM(G34:J34) -> 36624.4 | E109: =SUM(K34:N34) -> 54126.7 | F109: =F107*($F$68) -> 13367.828 | G109: =G107*($F$68) -> 14166.735 | H109: =H107*($F$68) -> 14918.962 | I109: =I107*($F$68) -> 15791.411 | J109: =J107*($F$68) -> 10064.025 | K109: =K107*($F$68) -> 9912.5737 | L109: =L107*($F$68) -> 10157.351 | M109: =M107*($F$68) -> 10414.367 | ... P109: =P107*($F$68) -> 11265.122
B110: R&D | C110: =SUM(C35:F35) -> 9313.4 | D110: =SUM(G35:J35) -> 10990.6 | E110: =SUM(K35:N35) -> 13337.3 | F110: =F109*$F$69 -> 2892.4348 | G110: =G109*$F$69 -> 3065.2966 | H110: =H109*$F$69 -> 3228.0579 | I110: =I109*$F$69 -> 3416.8323 | J110: =J109*$F$69 -> 2177.5816 | K110: =K109*$F$69 -> 2144.8116 | L110: =L109*$F$69 -> 2197.7747 | M110: =M109*$F$69 -> 2253.386 | ... P110: =P109*$F$69 -> 2437.4662
B111: SG&A | C111: =SUM(C36:F36) -> 7403.1 | D111: =SUM(G36:J36) -> 8593.8 | E111: =SUM(K36:N36) -> 11093.1 | F111: =F109*$F$70 -> 2417.7788 | G111: =G109*$F$70 -> 2562.2735 | H111: =H109*$F$70 -> 2698.3253 | I111: =I109*$F$70 -> 2856.1214 | J111: =J109*$F$70 -> 1820.2349 | K111: =K109*$F$70 -> 1792.8425 | L111: =L109*$F$70 -> 1837.1142 | M111: =M109*$F$70 -> 1883.5996 | ... P111: =P109*$F$70 -> 2037.4718
B112: IPR&D | C112: =SUM(C37:F37) -> 3799.8 | D112: =SUM(G37:J37) -> 3280.4 | E112: =SUM(K37:N37) -> 2909.5 | F112: =F109*$F$71 -> 481.24841 | G112: =G109*$F$71 -> 510.00946 | H112: =H109*$F$71 -> 537.08997 | I112: =I109*$F$71 -> 568.4986 | J112: =J109*$F$71 -> 362.30987 | K112: =K109*$F$71 -> 356.85754 | L112: =L109*$F$71 -> 365.66964 | M112: =M109*$F$71 -> 374.92234 | ... P112: =P109*$F$71 -> 405.54993
B113: Asset Impairement/Resturcturing | C113: =SUM(C38:F38) -> 67.7 | D113: =SUM(G38:J38) -> 860.6 | E113: =SUM(K38:N38) -> 484 | F113: =SUM(O38:P38) -> 982 | G113: =AVERAGE(C113:F113) -> 598.575 | H113: =AVERAGE(D113:G113) -> 731.29375 | I113: =AVERAGE(E113:H113) -> 698.96719 | J113: =AVERAGE(F113:I113) -> 752.70898 | K113: =AVERAGE(G113:J113) -> 695.38623 | L113: =AVERAGE(H113:K113) -> 719.58904 | M113: =AVERAGE(I113:L113) -> 716.66286 | N113: =AVERAGE(J113:M113) -> 721.08678 | ... P113: =AVERAGE(L113:O113) -> 717.62998
B114: Other expenses | C114: =SUM(C39:F39) -> 145.3 | D114: =SUM(G39:J39) -> 218.7 | E114: =SUM(K39:N39) -> 571 | F114: =SUM(O39:P39) -> -204 | G114: =AVERAGE(C114:F114) -> 182.75 | H114: =AVERAGE(D114:G114) -> 192.1125 | I114: =AVERAGE(E114:H114) -> 185.46562 | J114: =AVERAGE(F114:I114) -> 89.082031 | K114: =AVERAGE(G114:J114) -> 162.35254 | L114: =AVERAGE(H114:K114) -> 157.25317 | M114: =AVERAGE(I114:L114) -> 148.53834 | N114: =AVERAGE(J114:M114) -> 139.30652 | ... P114: =AVERAGE(L114:O114) -> 149.24017
...

Sheet Mounjaro
B2: Brand | C2: Mounjaro
B3: Generic | C3: TIRZEPATIDE
B4: Indication | C4: Type 2 Diabetes
B5: MOA | C5: Dual GIP/GLP-1 Receptor Agonist

Sheet Zepbound
B2: Brand | C2: Zepbound
B3: Generic | C3: Tirzepatide
B4: Indication | C4: Obesity & Obstructive Sleep Apnea
B5: MOA | C5: Dual GIP/GLP-1 Receptor Agonist

Sheet Trulicity
B2: Brand | C2: Trulicity
B3: Generic | C3: dulaglutide
B4: Indication | C4: Type-2 Diabetes
B5: MOA | C5: GLP-1 Agonist

Sheet Retatrutide
B2: Brand | C2: None
B3: Generic | C3: Retatrutide
B4: Indication | C4: Obesity & Type 2 Diabetes
B5: MOA | C5: GIP / GLP-1 / Glucagon Triple Receptor Agonist

Sheet Foundayo
B2: Brand | C2: Foundayo
B3: Generic | C3: Orforglipron
B4: Indication | C4: Obesity / Chronic Weight Management
B5: MOA | C5: GLP-1 Receptor Agonist (oral, nonpeptide)

Sheet Basaglar
B2: Brand | C2: Basaglar
B3: Generic | C3: Insulin Glargine
B4: Indication | C4: Type 1 and Type 2 Diabetes
B5: MOA | C5: Long-Acting Insulin

Sheet Humalog
B2: Brand | C2: Humalog
B3: Generic | C3: Insulin Lispro
B4: Indication | C4: Type 1 and Type 2 Diabetes
B5: MOA | C5: Rapid-Acting Insulin

Sheet Humulin
B2: Brand | C2: Humulin
B3: Generic | C3: Human Insulin
B4: Indication | C4: Type 1 and Type 2 Diabetes
B5: MOA | C5: Insulin (short- and intermediate-acting)

Sheet Jardiance
B2: Brand | C2: Jardiance
B3: Generic | C3: empagliflozin
B4: Indication | C4: Type 2 Diabetes & Heart Failure
B5: MOA | C5: SGLT2 Inhibitors

Sheet Verzenio
B2: Brand | C2: Verzenio
B3: Generic | C3: abemaciclib
B4: Indication | C4: Breast Cancer
B5: MOA | C5: CDK4/6 inhibitors

Sheet Cyramza
B2: Brand | C2: Cyramza
B3: Generic | C3: Ramucirumab
B4: Indication | C4: Gastric, NSCLC, and Colorectal Cancer
B5: MOA | C5: VEGFR2 Antagonist (Monoclonal Antibody)

Sheet Erbitux
B2: Brand | C2: Erbitux
B3: Generic | C3: Cetuximab
B4: Indication | C4: Colorectal and Head & Neck Cancer
B5: MOA | C5: EGFR Inhibitor (Monoclonal Antibody)

Sheet Retevmo
B2: Brand | C2: Retevmo
B3: Generic | C3: Selpercatinib
B4: Indication | C4: RET-Altered NSCLC and Thyroid Cancer
B5: MOA | C5: RET Kinase Inhibitor

Sheet Tyvyt
B2: Brand | C2: Tyvyt
B3: Generic | C3: Sintilimab
B4: Indication | C4: Hodgkin Lymphoma, NSCLC & other cancers (approved in China; not FDA-approved)
B5: MOA | C5: PD-1 Inhibitor (Monoclonal Antibody)

Sheet Jaypirca
B2: Brand | C2: Jaypirca
B3: Generic | C3: Pirtobrutinib
B4: Indication | C4: Non-Hodgkin Lymphoma
B5: MOA | C5: Bruton’s tyrosine kinase (BTK) inhibitor

Sheet Inluriyo
B2: Brand | C2: Inluriyo
B3: Generic | C3: Imlunestrant
B4: Indication | C4: Breast Cancer
B5: MOA | C5: Estrogen Antagonist

Sheet Ebglyss
B2: Brand | C2: Ebglyss
B3: Generic | C3: Lebrikizumab
B4: Indication | C4: Eczema
B5: MOA | C5: interleukin-13 antagonist

Sheet Olumiant
B2: Brand | C2: Olumiant
B3: Generic | C3: Baricitinib
B4: Indication | C4: Rheumatoid Arthritis, Alopecia Areata, COVID-19
B5: MOA | C5: JAK (Janus Kinase) Inhibitor

Sheet Omvoh
B2: Brand | C2: Omvoh
B3: Generic | C3: Mirikizumab-Mrkz
B4: Indication | C4: Crohn's Disease & Ulcerative Colitis
B5: MOA | C5: interleukin-23 antagonist

Sheet Taltz
B2: Brand | C2: Taltz
B3: Generic | C3: Ixekizumab
B4: Indication | C4: Plaque Psoriasis & Psoriatic Arthritis
B5: MOA | C5: interleukin antagonist

Sheet Emgality
B2: Brand | C2: Emgality
B3: Generic | C3: Galcanezumab
B4: Indication | C4: Migraine Prevention and Cluster Headache
B5: MOA | C5: CGRP Antagonist (Monoclonal Antibody)

Sheet Kisunla
B2: Brand | C2: Kisunla
B3: Generic | C3: donanemab-azbt
B4: Indication | C4: Alzheimer's Disease
B5: MOA | C5: amyloid beta-directed antibody
