Workbook

Sheet Main
A1: NioCorp (NB) | B1: (millions)
A2: Price | B2: 4.57
A3: Shares | B3: 45.072
A4: Market Cap | B4: =B2*B3 -> 205.97904
A5: Cash | B5: 25.5
A6: Debt | B6: 14.66
A7: EV | B7: =B4+B6-B5 -> 195.13904

Sheet Assumptions
A1: Assumptions
A3: Input | B3: Value | C3: Unit
A4: PROJECT
A5: Ore processed (LoM) | B5: 36655 | C5: kt
A6: Mine life | B6: 38 | C6: yrs
A7: Pre-production period | B7: 4 | C7: yrs
A8: Payable niobium (Nb) | B8: 171140 | C8: t
A9: Payable scandium (Sc2O3) | B9: 3676 | C9: t
A10: Payable titanium (TiO2) | B10: 431793 | C10: t
A11: PRICES
A12: Niobium price | B12: 46.55 | C12: $/kg
A13: Scandium oxide price | B13: 3674 | C13: $/kg
A14: Titanium dioxide price | B14: 0.99 | C14: $/kg
A15: COSTS
A16: Total operating cost | B16: 195.94 | C16: $/t ore
A17: Initial capital | B17: 1141 | C17: $M
A18: Sustaining capital | B18: 422 | C18: $M
A19: Closure & reclamation | B19: 44 | C19: $M
A20: Effective tax rate | B20: 0.1642 | C20: %
A21: Discount rate | B21: 0.08 | C21: %
A22: PUBLISHED RESULTS
A23: After-tax NPV @ 8% | B23: 2350 | C23: $M
A24: After-tax IRR | B24: 0.276 | C24: %
A25: Pre-tax NPV @ 8% | B25: 2800 | C25: $M
A26: Pre-tax IRR | B26: 0.292 | C26: %
A27: MARKET
A28: Cash & equivalents | B28: =Main!B5 -> 25.5 | C28: $M
A29: Warrants + options outstanding | B29: =(29985922+3020000)/1000000 -> 33.005922 | C29: M shares

Sheet NAV
A1: Project NAV
A3: REVENUE BUILD
A4: Product | B4: Payable (t) | C4: Price ($/kg) | D4: Rev ($M) | E4: % of Rev
A5: Niobium (Nb) | B5: =Assumptions!$B$8 -> 171140 | C5: =Assumptions!$B$12 -> 46.55 | D5: =B5*C5/1000 -> 7966.567 | E5: =D5/$D$8 -> 0.36377573
A6: Scandium (Sc2O3) | B6: =Assumptions!$B$9 -> 3676 | C6: =Assumptions!$B$13 -> 3674 | D6: =B6*C6/1000 -> 13505.624 | E6: =D6/$D$8 -> 0.61670456
A7: Titanium (TiO2) | B7: =Assumptions!$B$10 -> 431793 | C7: =Assumptions!$B$14 -> 0.99 | D7: =B7*C7/1000 -> 427.47507 | E7: =D7/$D$8 -> 0.019519707
A8: Total LoM revenue | D8: =SUM(D5:D7) -> 21899.666 | E8: =D8/$D$8 -> 1
A10: OPERATING & CAPITAL
A11: Total operating cost | B11: =Assumptions!$B$16*Assumptions!$B$5/1000 -> 7182.1807
A12: EBITDA (LoM) | B12: =D8-B11 -> 14717.485
A13: Effective tax rate | B13: =Assumptions!$B$20 -> 0.1642
A14: Initial capital | B14: =Assumptions!$B$17 -> 1141
A15: Sustaining capital | B15: =Assumptions!$B$18 -> 422
A16: Closure & reclamation | B16: =Assumptions!$B$19 -> 44
A17: Discount rate | B17: =Assumptions!$B$21 -> 0.08
A18: Production years | B18: =Assumptions!$B$6 -> 38
A19: Pre-production years | B19: =Assumptions!$B$7 -> 4
A22: ANNUAL CASH FLOW
A23: Year | C23: 1 | D23: 2 | E23: 3 | F23: 4 | G23: 5 | H23: 6 | I23: 7 | J23: 8 | K23: 9 | L23: 10 | M23: 11 | N23: 12 | O23: 13 | P23: 14 | Q23: 15 | R23: 16 | S23: 17 | T23: 18 | U23: 19 | V23: 20 | W23: 21 | X23: 22 | Y23: 23 | Z23: 24 | AA23: 25 | AB23: 26 | AC23: 27 | AD23: 28 | AE23: 29 | AF23: 30 | AG23: 31 | AH23: 32 | AI23: 33 | AJ23: 34 | AK23: 35 | AL23: 36 | AM23: 37 | AN23: 38 | AO23: 39 | AP23: 40 | AQ23: 41 | AR23: 42
A24: Phase | C24: Pre-prod | D24: Pre-prod | E24: Pre-prod | F24: Pre-prod | G24: Prod | H24: Prod | I24: Prod | J24: Prod | K24: Prod | L24: Prod | M24: Prod | N24: Prod | O24: Prod | P24: Prod | Q24: Prod | R24: Prod | S24: Prod | T24: Prod | U24: Prod | V24: Prod | W24: Prod | X24: Prod | Y24: Prod | Z24: Prod | AA24: Prod | AB24: Prod | AC24: Prod | AD24: Prod | AE24: Prod | AF24: Prod | AG24: Prod | AH24: Prod | AI24: Prod | AJ24: Prod | AK24: Prod | AL24: Prod | AM24: Prod | AN24: Prod | AO24: Prod | AP24: Prod | AQ24: Prod | AR24: Prod
A25: Revenue | C25: =IF(C23>$B$19,$D$8/$B$18,0) -> 0 | D25: =IF(D23>$B$19,$D$8/$B$18,0) -> 0 | E25: =IF(E23>$B$19,$D$8/$B$18,0) -> 0 | F25: =IF(F23>$B$19,$D$8/$B$18,0) -> 0 | G25: =IF(G23>$B$19,$D$8/$B$18,0) -> 576.307 | H25: =IF(H23>$B$19,$D$8/$B$18,0) -> 576.307 | I25: =IF(I23>$B$19,$D$8/$B$18,0) -> 576.307 | J25: =IF(J23>$B$19,$D$8/$B$18,0) -> 576.307 | ... AR25: =IF(AR23>$B$19,$D$8/$B$18,0) -> 576.307
A26: Operating cost | C26: =IF(C23>$B$19,-$B$11/$B$18,0) -> 0 | D26: =IF(D23>$B$19,-$B$11/$B$18,0) -> 0 | E26: =IF(E23>$B$19,-$B$11/$B$18,0) -> 0 | F26: =IF(F23>$B$19,-$B$11/$B$18,0) -> 0 | G26: =IF(G23>$B$19,-$B$11/$B$18,0) -> -189.00476 | H26: =IF(H23>$B$19,-$B$11/$B$18,0) -> -189.00476 | I26: =IF(I23>$B$19,-$B$11/$B$18,0) -> -189.00476 | J26: =IF(J23>$B$19,-$B$11/$B$18,0) -> -189.00476 | ... AR26: =IF(AR23>$B$19,-$B$11/$B$18,0) -> -189.00476
A27: EBITDA | C27: =C25+C26 -> 0 | D27: =D25+D26 -> 0 | E27: =E25+E26 -> 0 | F27: =F25+F26 -> 0 | G27: =G25+G26 -> 387.30225 | H27: =H25+H26 -> 387.30225 | I27: =I25+I26 -> 387.30225 | J27: =J25+J26 -> 387.30225 | ... AR27: =AR25+AR26 -> 387.30225
A28: Sustaining capex | C28: =IF(C23>$B$19,-$B$15/$B$18,0) -> 0 | D28: =IF(D23>$B$19,-$B$15/$B$18,0) -> 0 | E28: =IF(E23>$B$19,-$B$15/$B$18,0) -> 0 | F28: =IF(F23>$B$19,-$B$15/$B$18,0) -> 0 | G28: =IF(G23>$B$19,-$B$15/$B$18,0) -> -11.105263 | H28: =IF(H23>$B$19,-$B$15/$B$18,0) -> -11.105263 | I28: =IF(I23>$B$19,-$B$15/$B$18,0) -> -11.105263 | J28: =IF(J23>$B$19,-$B$15/$B$18,0) -> -11.105263 | ... AR28: =IF(AR23>$B$19,-$B$15/$B$18,0) -> -11.105263
A29: Op. profit (pre-tax) | C29: =C27+C28 -> 0 | D29: =D27+D28 -> 0 | E29: =E27+E28 -> 0 | F29: =F27+F28 -> 0 | G29: =G27+G28 -> 376.19698 | H29: =H27+H28 -> 376.19698 | I29: =I27+I28 -> 376.19698 | J29: =J27+J28 -> 376.19698 | ... AR29: =AR27+AR28 -> 376.19698
A30: Tax | C30: =-MAX(C29,0)*$B$13 -> 0 | D30: =-MAX(D29,0)*$B$13 -> 0 | E30: =-MAX(E29,0)*$B$13 -> 0 | F30: =-MAX(F29,0)*$B$13 -> 0 | G30: =-MAX(G29,0)*$B$13 -> -61.771545 | H30: =-MAX(H29,0)*$B$13 -> -61.771545 | I30: =-MAX(I29,0)*$B$13 -> -61.771545 | J30: =-MAX(J29,0)*$B$13 -> -61.771545 | ... AR30: =-MAX(AR29,0)*$B$13 -> -61.771545
A31: After-tax op. CF | C31: =C29+C30 -> 0 | D31: =D29+D30 -> 0 | E31: =E29+E30 -> 0 | F31: =F29+F30 -> 0 | G31: =G29+G30 -> 314.42544 | H31: =H29+H30 -> 314.42544 | I31: =I29+I30 -> 314.42544 | J31: =J29+J30 -> 314.42544 | ... AR31: =AR29+AR30 -> 314.42544
A32: Initial capex | C32: =IF(C23<=$B$19,-$B$14/$B$19,0) -> -285.25 | D32: =IF(D23<=$B$19,-$B$14/$B$19,0) -> -285.25 | E32: =IF(E23<=$B$19,-$B$14/$B$19,0) -> -285.25 | F32: =IF(F23<=$B$19,-$B$14/$B$19,0) -> -285.25 | G32: =IF(G23<=$B$19,-$B$14/$B$19,0) -> 0 | H32: =IF(H23<=$B$19,-$B$14/$B$19,0) -> 0 | I32: =IF(I23<=$B$19,-$B$14/$B$19,0) -> 0 | J32: =IF(J23<=$B$19,-$B$14/$B$19,0) -> 0 | ... AR32: =IF(AR23<=$B$19,-$B$14/$B$19,0) -> 0
A33: Closure | C33: =IF(C23=($B$18+$B$19),-$B$16,0) -> 0 | D33: =IF(D23=($B$18+$B$19),-$B$16,0) -> 0 | E33: =IF(E23=($B$18+$B$19),-$B$16,0) -> 0 | F33: =IF(F23=($B$18+$B$19),-$B$16,0) -> 0 | G33: =IF(G23=($B$18+$B$19),-$B$16,0) -> 0 | H33: =IF(H23=($B$18+$B$19),-$B$16,0) -> 0 | I33: =IF(I23=($B$18+$B$19),-$B$16,0) -> 0 | J33: =IF(J23=($B$18+$B$19),-$B$16,0) -> 0 | ... AR33: =IF(AR23=($B$18+$B$19),-$B$16,0) -> -44
A34: Free cash flow | C34: =C31+C32+C33 -> -285.25 | D34: =D31+D32+D33 -> -285.25 | E34: =E31+E32+E33 -> -285.25 | F34: =F31+F32+F33 -> -285.25 | G34: =G31+G32+G33 -> 314.42544 | H34: =H31+H32+H33 -> 314.42544 | I34: =I31+I32+I33 -> 314.42544 | J34: =J31+J32+J33 -> 314.42544 | ... AR34: =AR31+AR32+AR33 -> 270.42544
A35: Discount factor | C35: =1/(1+$B$17)^C23 -> 0.92592593 | D35: =1/(1+$B$17)^D23 -> 0.85733882 | E35: =1/(1+$B$17)^E23 -> 0.79383224 | F35: =1/(1+$B$17)^F23 -> 0.73502985 | G35: =1/(1+$B$17)^G23 -> 0.6805832 | H35: =1/(1+$B$17)^H23 -> 0.63016963 | I35: =1/(1+$B$17)^I23 -> 0.5834904 | J35: =1/(1+$B$17)^J23 -> 0.54026888 | ... AR35: =1/(1+$B$17)^AR23 -> 0.039464106
A36: PV of FCF | C36: =C34*C35 -> -264.12037 | D36: =D34*D35 -> -244.5559 | E36: =E34*E35 -> -226.44065 | F36: =F34*F35 -> -209.66727 | G36: =G34*G35 -> 213.99267 | H36: =H34*H35 -> 198.14136 | I36: =I34*I35 -> 183.46422 | J36: =J34*J35 -> 169.87428 | ... AR36: =AR34*AR35 -> 10.672098
A39: RESULTS
A40: Illustrative project NPV (this flat model) | B40: =SUM(C36:AR36) -> 1787.274
A41: Published after-tax NPV @ 8% | B41: =Assumptions!$B$23 -> 2350
A42: Difference | B42: =B40-B41 -> -562.72604
A43: Flat model as % of published | B43: =B40/B41 -> 0.76054211

Sheet Valuation
A1: Corporate NAV per Share
A3: MARKET SNAPSHOT
A4: Share price | B4: =Main!B2 -> 4.57
A5: Shares outstanding (M) | B5: =Main!B3 -> 45.072
A6: Market cap ($M) | B6: =B4*B5 -> 205.97904
A7: Net debt ($M) | B7: =Main!B6-Main!B5 -> -10.84
A9: PROJECT VALUE ANCHOR
A10: After-tax project NPV @ 8% ($M) | B10: =NAV!$B$41 -> 2350 | D10: Company published figure.
A11: NPV from NAV sheet | B11: =NAV!$B$40 -> 1787.274
A13: FINANCING OF INITIAL CAPITAL
A14: Initial capex to fund ($M) | B14: =Assumptions!$B$17 -> 1141
A15: % funded by equity | B15: 0.5
A16: % funded by debt / loan | B16: =1-B15 -> 0.5
A17: Equity to raise ($M) | B17: =B14*B15 -> 570.5
A18: Assumed raise price ($/sh) | B18: =Main!B2 -> 4.57
A19: New shares issued (M) | B19: =B17/B18 -> 124.83589
A20: Warrants + options (M) | B20: =Assumptions!$B$29 -> 33.005922
A21: Fully diluted shares (M) | B21: =B5+B19+B20 -> 202.91381
A23: EQUITY NAV
A24: Project NPV (after-tax) ($M) | B24: =B10 -> 2350
A25: + Cash & equivalents ($M) | B25: =Assumptions!$B$28 -> 25.5
A26: - Existing net debt ($M) | B26: =-B7 -> 10.84
A27: Equity NAV ($M) | B27: =B24+B25+B26 -> 2386.34
A28: NAV per fully diluted share ($) | B28: =B27/B21 -> 11.760363
A29: Current price ($) | B29: =B4 -> 4.57
A30: Implied upside / (downside) to 1.0x NAV | B30: =B28/B29-1 -> 1.5733835
A32: P/NAV LENS
A33: Implied price at 0.3x NAV | B33: =0.3*B28 -> 3.5281088
A34: Implied price at 0.5x NAV | B34: =0.5*B28 -> 5.8801814
A35: Implied price at 0.7x NAV | B35: =0.7*B28 -> 8.232254
A36: Current price implies P/NAV of | B36: =B29/B28 -> 0.38859345
